// 
// Decompiled by Procyon v0.5.34
// 

package com.google.android.gms.internal.ads;

import java.io.IOException;
import java.io.InputStream;

public class zzaj implements zzm
{
    private static final boolean DEBUG;
    @Deprecated
    private final zzar zzbo;
    private final zzai zzbp;
    private final zzak zzbq;
    
    static {
        DEBUG = zzaf.DEBUG;
    }
    
    public zzaj(final zzai zzai) {
        this(zzai, new zzak(4096));
    }
    
    private zzaj(final zzai zzai, final zzak zzbq) {
        this.zzbp = zzai;
        this.zzbo = zzai;
        this.zzbq = zzbq;
    }
    
    @Deprecated
    public zzaj(final zzar zzar) {
        this(zzar, new zzak(4096));
    }
    
    @Deprecated
    private zzaj(final zzar zzbo, final zzak zzbq) {
        this.zzbo = zzbo;
        this.zzbp = new zzah(zzbo);
        this.zzbq = zzbq;
    }
    
    private static void zza(final String s, final zzr<?> zzr, final zzae zzae) throws zzae {
        final zzab zzj = zzr.zzj();
        final int zzi = zzr.zzi();
        try {
            zzj.zza(zzae);
            zzr.zzb(String.format("%s-retry [timeout=%s]", s, zzi));
        }
        catch (zzae zzae) {
            zzr.zzb(String.format("%s-timeout-giveup [timeout=%s]", s, zzi));
            throw zzae;
        }
    }
    
    private final byte[] zza(final InputStream p0, final int p1) throws IOException, zzac {
        // 
        // This method could not be decompiled.
        // 
        // Original Bytecode:
        // 
        //     3: dup            
        //     4: aload_0        
        //     5: getfield        com/google/android/gms/internal/ads/zzaj.zzbq:Lcom/google/android/gms/internal/ads/zzak;
        //     8: iload_2        
        //     9: invokespecial   com/google/android/gms/internal/ads/zzau.<init>:(Lcom/google/android/gms/internal/ads/zzak;I)V
        //    12: astore          5
        //    14: aconst_null    
        //    15: astore_3       
        //    16: aload_1        
        //    17: ifnonnull       54
        //    20: new             Lcom/google/android/gms/internal/ads/zzac;
        //    23: dup            
        //    24: invokespecial   com/google/android/gms/internal/ads/zzac.<init>:()V
        //    27: athrow         
        //    28: astore          4
        //    30: aload_1        
        //    31: ifnull          38
        //    34: aload_1        
        //    35: invokevirtual   java/io/InputStream.close:()V
        //    38: aload_0        
        //    39: getfield        com/google/android/gms/internal/ads/zzaj.zzbq:Lcom/google/android/gms/internal/ads/zzak;
        //    42: aload_3        
        //    43: invokevirtual   com/google/android/gms/internal/ads/zzak.zza:([B)V
        //    46: aload           5
        //    48: invokevirtual   com/google/android/gms/internal/ads/zzau.close:()V
        //    51: aload           4
        //    53: athrow         
        //    54: aload_0        
        //    55: getfield        com/google/android/gms/internal/ads/zzaj.zzbq:Lcom/google/android/gms/internal/ads/zzak;
        //    58: sipush          1024
        //    61: invokevirtual   com/google/android/gms/internal/ads/zzak.zzb:(I)[B
        //    64: astore          4
        //    66: aload           4
        //    68: astore_3       
        //    69: aload_1        
        //    70: aload           4
        //    72: invokevirtual   java/io/InputStream.read:([B)I
        //    75: istore_2       
        //    76: iload_2        
        //    77: iconst_m1      
        //    78: if_icmpeq       96
        //    81: aload           4
        //    83: astore_3       
        //    84: aload           5
        //    86: aload           4
        //    88: iconst_0       
        //    89: iload_2        
        //    90: invokevirtual   com/google/android/gms/internal/ads/zzau.write:([BII)V
        //    93: goto            66
        //    96: aload           4
        //    98: astore_3       
        //    99: aload           5
        //   101: invokevirtual   com/google/android/gms/internal/ads/zzau.toByteArray:()[B
        //   104: astore          6
        //   106: aload_1        
        //   107: ifnull          114
        //   110: aload_1        
        //   111: invokevirtual   java/io/InputStream.close:()V
        //   114: aload_0        
        //   115: getfield        com/google/android/gms/internal/ads/zzaj.zzbq:Lcom/google/android/gms/internal/ads/zzak;
        //   118: aload           4
        //   120: invokevirtual   com/google/android/gms/internal/ads/zzak.zza:([B)V
        //   123: aload           5
        //   125: invokevirtual   com/google/android/gms/internal/ads/zzau.close:()V
        //   128: aload           6
        //   130: areturn        
        //   131: astore_1       
        //   132: ldc             "Error occurred when closing InputStream"
        //   134: iconst_0       
        //   135: anewarray       Ljava/lang/Object;
        //   138: invokestatic    com/google/android/gms/internal/ads/zzaf.v:(Ljava/lang/String;[Ljava/lang/Object;)V
        //   141: goto            114
        //   144: astore_1       
        //   145: ldc             "Error occurred when closing InputStream"
        //   147: iconst_0       
        //   148: anewarray       Ljava/lang/Object;
        //   151: invokestatic    com/google/android/gms/internal/ads/zzaf.v:(Ljava/lang/String;[Ljava/lang/Object;)V
        //   154: goto            38
        //    Exceptions:
        //  throws java.io.IOException
        //  throws com.google.android.gms.internal.ads.zzac
        //    Exceptions:
        //  Try           Handler
        //  Start  End    Start  End    Type                 
        //  -----  -----  -----  -----  ---------------------
        //  20     28     28     54     Any
        //  34     38     144    157    Ljava/io/IOException;
        //  54     66     28     54     Any
        //  69     76     28     54     Any
        //  84     93     28     54     Any
        //  99     106    28     54     Any
        //  110    114    131    144    Ljava/io/IOException;
        // 
        // The error that occurred was:
        // 
        // java.lang.IllegalStateException: Expression is linked from several locations: Label_0038:
        //     at com.strobel.decompiler.ast.Error.expressionLinkedFromMultipleLocations(Error.java:27)
        //     at com.strobel.decompiler.ast.AstOptimizer.mergeDisparateObjectInitializations(AstOptimizer.java:2596)
        //     at com.strobel.decompiler.ast.AstOptimizer.optimize(AstOptimizer.java:235)
        //     at com.strobel.decompiler.ast.AstOptimizer.optimize(AstOptimizer.java:42)
        //     at com.strobel.decompiler.languages.java.ast.AstMethodBodyBuilder.createMethodBody(AstMethodBodyBuilder.java:214)
        //     at com.strobel.decompiler.languages.java.ast.AstMethodBodyBuilder.createMethodBody(AstMethodBodyBuilder.java:99)
        //     at com.strobel.decompiler.languages.java.ast.AstBuilder.createMethodBody(AstBuilder.java:782)
        //     at com.strobel.decompiler.languages.java.ast.AstBuilder.createMethod(AstBuilder.java:675)
        //     at com.strobel.decompiler.languages.java.ast.AstBuilder.addTypeMembers(AstBuilder.java:552)
        //     at com.strobel.decompiler.languages.java.ast.AstBuilder.createTypeCore(AstBuilder.java:519)
        //     at com.strobel.decompiler.languages.java.ast.AstBuilder.createTypeNoCache(AstBuilder.java:161)
        //     at com.strobel.decompiler.languages.java.ast.AstBuilder.createType(AstBuilder.java:150)
        //     at com.strobel.decompiler.languages.java.ast.AstBuilder.addType(AstBuilder.java:125)
        //     at com.strobel.decompiler.languages.java.JavaLanguage.buildAst(JavaLanguage.java:71)
        //     at com.strobel.decompiler.languages.java.JavaLanguage.decompileType(JavaLanguage.java:59)
        //     at com.strobel.decompiler.DecompilerDriver.decompileType(DecompilerDriver.java:330)
        //     at com.strobel.decompiler.DecompilerDriver.decompileJar(DecompilerDriver.java:251)
        //     at com.strobel.decompiler.DecompilerDriver.main(DecompilerDriver.java:126)
        // 
        throw new IllegalStateException("An error occurred while decompiling this method.");
    }
    
    @Override
    public zzp zzc(final zzr<?> p0) throws zzae {
        // 
        // This method could not be decompiled.
        // 
        // Original Bytecode:
        // 
        //     3: lstore_3       
        //     4: aconst_null    
        //     5: astore          9
        //     7: invokestatic    java/util/Collections.emptyList:()Ljava/util/List;
        //    10: astore          10
        //    12: aload_1        
        //    13: invokevirtual   com/google/android/gms/internal/ads/zzr.zzf:()Lcom/google/android/gms/internal/ads/zzc;
        //    16: astore          11
        //    18: aload           11
        //    20: ifnonnull       111
        //    23: invokestatic    java/util/Collections.emptyMap:()Ljava/util/Map;
        //    26: astore          7
        //    28: aload_0        
        //    29: getfield        com/google/android/gms/internal/ads/zzaj.zzbp:Lcom/google/android/gms/internal/ads/zzai;
        //    32: aload_1        
        //    33: aload           7
        //    35: invokevirtual   com/google/android/gms/internal/ads/zzai.zza:(Lcom/google/android/gms/internal/ads/zzr;Ljava/util/Map;)Lcom/google/android/gms/internal/ads/zzaq;
        //    38: astore          8
        //    40: aload           10
        //    42: astore          7
        //    44: aload           8
        //    46: invokevirtual   com/google/android/gms/internal/ads/zzaq.getStatusCode:()I
        //    49: istore_2       
        //    50: aload           10
        //    52: astore          7
        //    54: aload           8
        //    56: invokevirtual   com/google/android/gms/internal/ads/zzaq.zzq:()Ljava/util/List;
        //    59: astore          10
        //    61: iload_2        
        //    62: sipush          304
        //    65: if_icmpne       720
        //    68: aload           10
        //    70: astore          7
        //    72: aload_1        
        //    73: invokevirtual   com/google/android/gms/internal/ads/zzr.zzf:()Lcom/google/android/gms/internal/ads/zzc;
        //    76: astore          9
        //    78: aload           9
        //    80: ifnonnull       200
        //    83: aload           10
        //    85: astore          7
        //    87: new             Lcom/google/android/gms/internal/ads/zzp;
        //    90: dup            
        //    91: sipush          304
        //    94: aconst_null    
        //    95: iconst_1       
        //    96: invokestatic    android/os/SystemClock.elapsedRealtime:()J
        //    99: lload_3        
        //   100: lsub           
        //   101: aload           10
        //   103: invokespecial   com/google/android/gms/internal/ads/zzp.<init>:(I[BZJLjava/util/List;)V
        //   106: astore          9
        //   108: aload           9
        //   110: areturn        
        //   111: new             Ljava/util/HashMap;
        //   114: dup            
        //   115: invokespecial   java/util/HashMap.<init>:()V
        //   118: astore          8
        //   120: aload           11
        //   122: getfield        com/google/android/gms/internal/ads/zzc.zza:Ljava/lang/String;
        //   125: ifnull          143
        //   128: aload           8
        //   130: ldc             "If-None-Match"
        //   132: aload           11
        //   134: getfield        com/google/android/gms/internal/ads/zzc.zza:Ljava/lang/String;
        //   137: invokeinterface java/util/Map.put:(Ljava/lang/Object;Ljava/lang/Object;)Ljava/lang/Object;
        //   142: pop            
        //   143: aload           8
        //   145: astore          7
        //   147: aload           11
        //   149: getfield        com/google/android/gms/internal/ads/zzc.zzc:J
        //   152: lconst_0       
        //   153: lcmp           
        //   154: ifle            28
        //   157: aload           8
        //   159: ldc             "If-Modified-Since"
        //   161: aload           11
        //   163: getfield        com/google/android/gms/internal/ads/zzc.zzc:J
        //   166: invokestatic    com/google/android/gms/internal/ads/zzap.zzb:(J)Ljava/lang/String;
        //   169: invokeinterface java/util/Map.put:(Ljava/lang/Object;Ljava/lang/Object;)Ljava/lang/Object;
        //   174: pop            
        //   175: aload           8
        //   177: astore          7
        //   179: goto            28
        //   182: astore          7
        //   184: ldc             "socket"
        //   186: aload_1        
        //   187: new             Lcom/google/android/gms/internal/ads/zzad;
        //   190: dup            
        //   191: invokespecial   com/google/android/gms/internal/ads/zzad.<init>:()V
        //   194: invokestatic    com/google/android/gms/internal/ads/zzaj.zza:(Ljava/lang/String;Lcom/google/android/gms/internal/ads/zzr;Lcom/google/android/gms/internal/ads/zzae;)V
        //   197: goto            4
        //   200: aload           10
        //   202: astore          7
        //   204: new             Ljava/util/TreeSet;
        //   207: dup            
        //   208: getstatic       java/lang/String.CASE_INSENSITIVE_ORDER:Ljava/util/Comparator;
        //   211: invokespecial   java/util/TreeSet.<init>:(Ljava/util/Comparator;)V
        //   214: astore          11
        //   216: aload           10
        //   218: astore          7
        //   220: aload           10
        //   222: invokeinterface java/util/List.isEmpty:()Z
        //   227: ifne            321
        //   230: aload           10
        //   232: astore          7
        //   234: aload           10
        //   236: invokeinterface java/util/List.iterator:()Ljava/util/Iterator;
        //   241: astore          12
        //   243: aload           10
        //   245: astore          7
        //   247: aload           12
        //   249: invokeinterface java/util/Iterator.hasNext:()Z
        //   254: ifeq            321
        //   257: aload           10
        //   259: astore          7
        //   261: aload           11
        //   263: aload           12
        //   265: invokeinterface java/util/Iterator.next:()Ljava/lang/Object;
        //   270: checkcast       Lcom/google/android/gms/internal/ads/zzl;
        //   273: invokevirtual   com/google/android/gms/internal/ads/zzl.getName:()Ljava/lang/String;
        //   276: invokeinterface java/util/Set.add:(Ljava/lang/Object;)Z
        //   281: pop            
        //   282: goto            243
        //   285: astore          7
        //   287: aload_1        
        //   288: invokevirtual   com/google/android/gms/internal/ads/zzr.getUrl:()Ljava/lang/String;
        //   291: invokestatic    java/lang/String.valueOf:(Ljava/lang/Object;)Ljava/lang/String;
        //   294: astore_1       
        //   295: aload_1        
        //   296: invokevirtual   java/lang/String.length:()I
        //   299: ifeq            912
        //   302: ldc_w           "Bad URL "
        //   305: aload_1        
        //   306: invokevirtual   java/lang/String.concat:(Ljava/lang/String;)Ljava/lang/String;
        //   309: astore_1       
        //   310: new             Ljava/lang/RuntimeException;
        //   313: dup            
        //   314: aload_1        
        //   315: aload           7
        //   317: invokespecial   java/lang/RuntimeException.<init>:(Ljava/lang/String;Ljava/lang/Throwable;)V
        //   320: athrow         
        //   321: aload           10
        //   323: astore          7
        //   325: new             Ljava/util/ArrayList;
        //   328: dup            
        //   329: aload           10
        //   331: invokespecial   java/util/ArrayList.<init>:(Ljava/util/Collection;)V
        //   334: astore          12
        //   336: aload           10
        //   338: astore          7
        //   340: aload           9
        //   342: getfield        com/google/android/gms/internal/ads/zzc.zzg:Ljava/util/List;
        //   345: ifnull          561
        //   348: aload           10
        //   350: astore          7
        //   352: aload           9
        //   354: getfield        com/google/android/gms/internal/ads/zzc.zzg:Ljava/util/List;
        //   357: invokeinterface java/util/List.isEmpty:()Z
        //   362: ifne            692
        //   365: aload           10
        //   367: astore          7
        //   369: aload           9
        //   371: getfield        com/google/android/gms/internal/ads/zzc.zzg:Ljava/util/List;
        //   374: invokeinterface java/util/List.iterator:()Ljava/util/Iterator;
        //   379: astore          13
        //   381: aload           10
        //   383: astore          7
        //   385: aload           13
        //   387: invokeinterface java/util/Iterator.hasNext:()Z
        //   392: ifeq            692
        //   395: aload           10
        //   397: astore          7
        //   399: aload           13
        //   401: invokeinterface java/util/Iterator.next:()Ljava/lang/Object;
        //   406: checkcast       Lcom/google/android/gms/internal/ads/zzl;
        //   409: astore          14
        //   411: aload           10
        //   413: astore          7
        //   415: aload           11
        //   417: aload           14
        //   419: invokevirtual   com/google/android/gms/internal/ads/zzl.getName:()Ljava/lang/String;
        //   422: invokeinterface java/util/Set.contains:(Ljava/lang/Object;)Z
        //   427: ifne            381
        //   430: aload           10
        //   432: astore          7
        //   434: aload           12
        //   436: aload           14
        //   438: invokeinterface java/util/List.add:(Ljava/lang/Object;)Z
        //   443: pop            
        //   444: goto            381
        //   447: astore          11
        //   449: aconst_null    
        //   450: astore          9
        //   452: aload           7
        //   454: astore          10
        //   456: aload           9
        //   458: astore          7
        //   460: aload           8
        //   462: astore          9
        //   464: aload           11
        //   466: astore          8
        //   468: aload           9
        //   470: ifnull          926
        //   473: aload           9
        //   475: invokevirtual   com/google/android/gms/internal/ads/zzaq.getStatusCode:()I
        //   478: istore_2       
        //   479: ldc_w           "Unexpected response code %d for %s"
        //   482: iconst_2       
        //   483: anewarray       Ljava/lang/Object;
        //   486: dup            
        //   487: iconst_0       
        //   488: iload_2        
        //   489: invokestatic    java/lang/Integer.valueOf:(I)Ljava/lang/Integer;
        //   492: aastore        
        //   493: dup            
        //   494: iconst_1       
        //   495: aload_1        
        //   496: invokevirtual   com/google/android/gms/internal/ads/zzr.getUrl:()Ljava/lang/String;
        //   499: aastore        
        //   500: invokestatic    com/google/android/gms/internal/ads/zzaf.e:(Ljava/lang/String;[Ljava/lang/Object;)V
        //   503: aload           7
        //   505: ifnull          994
        //   508: new             Lcom/google/android/gms/internal/ads/zzp;
        //   511: dup            
        //   512: iload_2        
        //   513: aload           7
        //   515: iconst_0       
        //   516: invokestatic    android/os/SystemClock.elapsedRealtime:()J
        //   519: lload_3        
        //   520: lsub           
        //   521: aload           10
        //   523: invokespecial   com/google/android/gms/internal/ads/zzp.<init>:(I[BZJLjava/util/List;)V
        //   526: astore          7
        //   528: iload_2        
        //   529: sipush          401
        //   532: if_icmpeq       542
        //   535: iload_2        
        //   536: sipush          403
        //   539: if_icmpne       936
        //   542: ldc_w           "auth"
        //   545: aload_1        
        //   546: new             Lcom/google/android/gms/internal/ads/zza;
        //   549: dup            
        //   550: aload           7
        //   552: invokespecial   com/google/android/gms/internal/ads/zza.<init>:(Lcom/google/android/gms/internal/ads/zzp;)V
        //   555: invokestatic    com/google/android/gms/internal/ads/zzaj.zza:(Ljava/lang/String;Lcom/google/android/gms/internal/ads/zzr;Lcom/google/android/gms/internal/ads/zzae;)V
        //   558: goto            4
        //   561: aload           10
        //   563: astore          7
        //   565: aload           9
        //   567: getfield        com/google/android/gms/internal/ads/zzc.zzf:Ljava/util/Map;
        //   570: invokeinterface java/util/Map.isEmpty:()Z
        //   575: ifne            692
        //   578: aload           10
        //   580: astore          7
        //   582: aload           9
        //   584: getfield        com/google/android/gms/internal/ads/zzc.zzf:Ljava/util/Map;
        //   587: invokeinterface java/util/Map.entrySet:()Ljava/util/Set;
        //   592: invokeinterface java/util/Set.iterator:()Ljava/util/Iterator;
        //   597: astore          13
        //   599: aload           10
        //   601: astore          7
        //   603: aload           13
        //   605: invokeinterface java/util/Iterator.hasNext:()Z
        //   610: ifeq            692
        //   613: aload           10
        //   615: astore          7
        //   617: aload           13
        //   619: invokeinterface java/util/Iterator.next:()Ljava/lang/Object;
        //   624: checkcast       Ljava/util/Map$Entry;
        //   627: astore          14
        //   629: aload           10
        //   631: astore          7
        //   633: aload           11
        //   635: aload           14
        //   637: invokeinterface java/util/Map$Entry.getKey:()Ljava/lang/Object;
        //   642: invokeinterface java/util/Set.contains:(Ljava/lang/Object;)Z
        //   647: ifne            599
        //   650: aload           10
        //   652: astore          7
        //   654: aload           12
        //   656: new             Lcom/google/android/gms/internal/ads/zzl;
        //   659: dup            
        //   660: aload           14
        //   662: invokeinterface java/util/Map$Entry.getKey:()Ljava/lang/Object;
        //   667: checkcast       Ljava/lang/String;
        //   670: aload           14
        //   672: invokeinterface java/util/Map$Entry.getValue:()Ljava/lang/Object;
        //   677: checkcast       Ljava/lang/String;
        //   680: invokespecial   com/google/android/gms/internal/ads/zzl.<init>:(Ljava/lang/String;Ljava/lang/String;)V
        //   683: invokeinterface java/util/List.add:(Ljava/lang/Object;)Z
        //   688: pop            
        //   689: goto            599
        //   692: aload           10
        //   694: astore          7
        //   696: new             Lcom/google/android/gms/internal/ads/zzp;
        //   699: dup            
        //   700: sipush          304
        //   703: aload           9
        //   705: getfield        com/google/android/gms/internal/ads/zzc.data:[B
        //   708: iconst_1       
        //   709: invokestatic    android/os/SystemClock.elapsedRealtime:()J
        //   712: lload_3        
        //   713: lsub           
        //   714: aload           12
        //   716: invokespecial   com/google/android/gms/internal/ads/zzp.<init>:(I[BZJLjava/util/List;)V
        //   719: areturn        
        //   720: aload           10
        //   722: astore          7
        //   724: aload           8
        //   726: invokevirtual   com/google/android/gms/internal/ads/zzaq.getContent:()Ljava/io/InputStream;
        //   729: astore          9
        //   731: aload           9
        //   733: ifnull          865
        //   736: aload           10
        //   738: astore          7
        //   740: aload_0        
        //   741: aload           9
        //   743: aload           8
        //   745: invokevirtual   com/google/android/gms/internal/ads/zzaq.getContentLength:()I
        //   748: invokespecial   com/google/android/gms/internal/ads/zzaj.zza:(Ljava/io/InputStream;I)[B
        //   751: astore          9
        //   753: aload           9
        //   755: astore          7
        //   757: invokestatic    android/os/SystemClock.elapsedRealtime:()J
        //   760: lload_3        
        //   761: lsub           
        //   762: lstore          5
        //   764: getstatic       com/google/android/gms/internal/ads/zzaj.DEBUG:Z
        //   767: ifne            779
        //   770: lload           5
        //   772: ldc2_w          3000
        //   775: lcmp           
        //   776: ifle            1019
        //   779: aload           7
        //   781: ifnull          881
        //   784: aload           7
        //   786: arraylength    
        //   787: invokestatic    java/lang/Integer.valueOf:(I)Ljava/lang/Integer;
        //   790: astore          9
        //   792: ldc_w           "HTTP response for request=<%s> [lifetime=%d], [size=%s], [rc=%d], [retryCount=%s]"
        //   795: iconst_5       
        //   796: anewarray       Ljava/lang/Object;
        //   799: dup            
        //   800: iconst_0       
        //   801: aload_1        
        //   802: aastore        
        //   803: dup            
        //   804: iconst_1       
        //   805: lload           5
        //   807: invokestatic    java/lang/Long.valueOf:(J)Ljava/lang/Long;
        //   810: aastore        
        //   811: dup            
        //   812: iconst_2       
        //   813: aload           9
        //   815: aastore        
        //   816: dup            
        //   817: iconst_3       
        //   818: iload_2        
        //   819: invokestatic    java/lang/Integer.valueOf:(I)Ljava/lang/Integer;
        //   822: aastore        
        //   823: dup            
        //   824: iconst_4       
        //   825: aload_1        
        //   826: invokevirtual   com/google/android/gms/internal/ads/zzr.zzj:()Lcom/google/android/gms/internal/ads/zzab;
        //   829: invokeinterface com/google/android/gms/internal/ads/zzab.zzd:()I
        //   834: invokestatic    java/lang/Integer.valueOf:(I)Ljava/lang/Integer;
        //   837: aastore        
        //   838: invokestatic    com/google/android/gms/internal/ads/zzaf.d:(Ljava/lang/String;[Ljava/lang/Object;)V
        //   841: goto            1019
        //   844: new             Ljava/io/IOException;
        //   847: dup            
        //   848: invokespecial   java/io/IOException.<init>:()V
        //   851: athrow         
        //   852: astore          11
        //   854: aload           8
        //   856: astore          9
        //   858: aload           11
        //   860: astore          8
        //   862: goto            468
        //   865: aload           10
        //   867: astore          7
        //   869: iconst_0       
        //   870: newarray        B
        //   872: astore          9
        //   874: aload           9
        //   876: astore          7
        //   878: goto            757
        //   881: ldc_w           "null"
        //   884: astore          9
        //   886: goto            792
        //   889: new             Lcom/google/android/gms/internal/ads/zzp;
        //   892: dup            
        //   893: iload_2        
        //   894: aload           7
        //   896: iconst_0       
        //   897: invokestatic    android/os/SystemClock.elapsedRealtime:()J
        //   900: lload_3        
        //   901: lsub           
        //   902: aload           10
        //   904: invokespecial   com/google/android/gms/internal/ads/zzp.<init>:(I[BZJLjava/util/List;)V
        //   907: astore          9
        //   909: aload           9
        //   911: areturn        
        //   912: new             Ljava/lang/String;
        //   915: dup            
        //   916: ldc_w           "Bad URL "
        //   919: invokespecial   java/lang/String.<init>:(Ljava/lang/String;)V
        //   922: astore_1       
        //   923: goto            310
        //   926: new             Lcom/google/android/gms/internal/ads/zzq;
        //   929: dup            
        //   930: aload           8
        //   932: invokespecial   com/google/android/gms/internal/ads/zzq.<init>:(Ljava/lang/Throwable;)V
        //   935: athrow         
        //   936: iload_2        
        //   937: sipush          400
        //   940: if_icmplt       960
        //   943: iload_2        
        //   944: sipush          499
        //   947: if_icmpgt       960
        //   950: new             Lcom/google/android/gms/internal/ads/zzg;
        //   953: dup            
        //   954: aload           7
        //   956: invokespecial   com/google/android/gms/internal/ads/zzg.<init>:(Lcom/google/android/gms/internal/ads/zzp;)V
        //   959: athrow         
        //   960: iload_2        
        //   961: sipush          500
        //   964: if_icmplt       984
        //   967: iload_2        
        //   968: sipush          599
        //   971: if_icmpgt       984
        //   974: new             Lcom/google/android/gms/internal/ads/zzac;
        //   977: dup            
        //   978: aload           7
        //   980: invokespecial   com/google/android/gms/internal/ads/zzac.<init>:(Lcom/google/android/gms/internal/ads/zzp;)V
        //   983: athrow         
        //   984: new             Lcom/google/android/gms/internal/ads/zzac;
        //   987: dup            
        //   988: aload           7
        //   990: invokespecial   com/google/android/gms/internal/ads/zzac.<init>:(Lcom/google/android/gms/internal/ads/zzp;)V
        //   993: athrow         
        //   994: ldc_w           "network"
        //   997: aload_1        
        //   998: new             Lcom/google/android/gms/internal/ads/zzo;
        //  1001: dup            
        //  1002: invokespecial   com/google/android/gms/internal/ads/zzo.<init>:()V
        //  1005: invokestatic    com/google/android/gms/internal/ads/zzaj.zza:(Ljava/lang/String;Lcom/google/android/gms/internal/ads/zzr;Lcom/google/android/gms/internal/ads/zzae;)V
        //  1008: goto            4
        //  1011: astore          8
        //  1013: aconst_null    
        //  1014: astore          7
        //  1016: goto            468
        //  1019: iload_2        
        //  1020: sipush          200
        //  1023: if_icmplt       844
        //  1026: iload_2        
        //  1027: sipush          299
        //  1030: if_icmple       889
        //  1033: goto            844
        //    Exceptions:
        //  throws com.google.android.gms.internal.ads.zzae
        //    Signature:
        //  (Lcom/google/android/gms/internal/ads/zzr<*>;)Lcom/google/android/gms/internal/ads/zzp;
        //    Exceptions:
        //  Try           Handler
        //  Start  End    Start  End    Type                             
        //  -----  -----  -----  -----  ---------------------------------
        //  12     18     182    200    Ljava/net/SocketTimeoutException;
        //  12     18     285    321    Ljava/net/MalformedURLException;
        //  12     18     1011   1019   Ljava/io/IOException;
        //  23     28     182    200    Ljava/net/SocketTimeoutException;
        //  23     28     285    321    Ljava/net/MalformedURLException;
        //  23     28     1011   1019   Ljava/io/IOException;
        //  28     40     182    200    Ljava/net/SocketTimeoutException;
        //  28     40     285    321    Ljava/net/MalformedURLException;
        //  28     40     1011   1019   Ljava/io/IOException;
        //  44     50     182    200    Ljava/net/SocketTimeoutException;
        //  44     50     285    321    Ljava/net/MalformedURLException;
        //  44     50     447    468    Ljava/io/IOException;
        //  54     61     182    200    Ljava/net/SocketTimeoutException;
        //  54     61     285    321    Ljava/net/MalformedURLException;
        //  54     61     447    468    Ljava/io/IOException;
        //  72     78     182    200    Ljava/net/SocketTimeoutException;
        //  72     78     285    321    Ljava/net/MalformedURLException;
        //  72     78     447    468    Ljava/io/IOException;
        //  87     108    182    200    Ljava/net/SocketTimeoutException;
        //  87     108    285    321    Ljava/net/MalformedURLException;
        //  87     108    447    468    Ljava/io/IOException;
        //  111    143    182    200    Ljava/net/SocketTimeoutException;
        //  111    143    285    321    Ljava/net/MalformedURLException;
        //  111    143    1011   1019   Ljava/io/IOException;
        //  147    175    182    200    Ljava/net/SocketTimeoutException;
        //  147    175    285    321    Ljava/net/MalformedURLException;
        //  147    175    1011   1019   Ljava/io/IOException;
        //  204    216    182    200    Ljava/net/SocketTimeoutException;
        //  204    216    285    321    Ljava/net/MalformedURLException;
        //  204    216    447    468    Ljava/io/IOException;
        //  220    230    182    200    Ljava/net/SocketTimeoutException;
        //  220    230    285    321    Ljava/net/MalformedURLException;
        //  220    230    447    468    Ljava/io/IOException;
        //  234    243    182    200    Ljava/net/SocketTimeoutException;
        //  234    243    285    321    Ljava/net/MalformedURLException;
        //  234    243    447    468    Ljava/io/IOException;
        //  247    257    182    200    Ljava/net/SocketTimeoutException;
        //  247    257    285    321    Ljava/net/MalformedURLException;
        //  247    257    447    468    Ljava/io/IOException;
        //  261    282    182    200    Ljava/net/SocketTimeoutException;
        //  261    282    285    321    Ljava/net/MalformedURLException;
        //  261    282    447    468    Ljava/io/IOException;
        //  325    336    182    200    Ljava/net/SocketTimeoutException;
        //  325    336    285    321    Ljava/net/MalformedURLException;
        //  325    336    447    468    Ljava/io/IOException;
        //  340    348    182    200    Ljava/net/SocketTimeoutException;
        //  340    348    285    321    Ljava/net/MalformedURLException;
        //  340    348    447    468    Ljava/io/IOException;
        //  352    365    182    200    Ljava/net/SocketTimeoutException;
        //  352    365    285    321    Ljava/net/MalformedURLException;
        //  352    365    447    468    Ljava/io/IOException;
        //  369    381    182    200    Ljava/net/SocketTimeoutException;
        //  369    381    285    321    Ljava/net/MalformedURLException;
        //  369    381    447    468    Ljava/io/IOException;
        //  385    395    182    200    Ljava/net/SocketTimeoutException;
        //  385    395    285    321    Ljava/net/MalformedURLException;
        //  385    395    447    468    Ljava/io/IOException;
        //  399    411    182    200    Ljava/net/SocketTimeoutException;
        //  399    411    285    321    Ljava/net/MalformedURLException;
        //  399    411    447    468    Ljava/io/IOException;
        //  415    430    182    200    Ljava/net/SocketTimeoutException;
        //  415    430    285    321    Ljava/net/MalformedURLException;
        //  415    430    447    468    Ljava/io/IOException;
        //  434    444    182    200    Ljava/net/SocketTimeoutException;
        //  434    444    285    321    Ljava/net/MalformedURLException;
        //  434    444    447    468    Ljava/io/IOException;
        //  565    578    182    200    Ljava/net/SocketTimeoutException;
        //  565    578    285    321    Ljava/net/MalformedURLException;
        //  565    578    447    468    Ljava/io/IOException;
        //  582    599    182    200    Ljava/net/SocketTimeoutException;
        //  582    599    285    321    Ljava/net/MalformedURLException;
        //  582    599    447    468    Ljava/io/IOException;
        //  603    613    182    200    Ljava/net/SocketTimeoutException;
        //  603    613    285    321    Ljava/net/MalformedURLException;
        //  603    613    447    468    Ljava/io/IOException;
        //  617    629    182    200    Ljava/net/SocketTimeoutException;
        //  617    629    285    321    Ljava/net/MalformedURLException;
        //  617    629    447    468    Ljava/io/IOException;
        //  633    650    182    200    Ljava/net/SocketTimeoutException;
        //  633    650    285    321    Ljava/net/MalformedURLException;
        //  633    650    447    468    Ljava/io/IOException;
        //  654    689    182    200    Ljava/net/SocketTimeoutException;
        //  654    689    285    321    Ljava/net/MalformedURLException;
        //  654    689    447    468    Ljava/io/IOException;
        //  696    720    182    200    Ljava/net/SocketTimeoutException;
        //  696    720    285    321    Ljava/net/MalformedURLException;
        //  696    720    447    468    Ljava/io/IOException;
        //  724    731    182    200    Ljava/net/SocketTimeoutException;
        //  724    731    285    321    Ljava/net/MalformedURLException;
        //  724    731    447    468    Ljava/io/IOException;
        //  740    753    182    200    Ljava/net/SocketTimeoutException;
        //  740    753    285    321    Ljava/net/MalformedURLException;
        //  740    753    447    468    Ljava/io/IOException;
        //  757    770    182    200    Ljava/net/SocketTimeoutException;
        //  757    770    285    321    Ljava/net/MalformedURLException;
        //  757    770    852    865    Ljava/io/IOException;
        //  784    792    182    200    Ljava/net/SocketTimeoutException;
        //  784    792    285    321    Ljava/net/MalformedURLException;
        //  784    792    852    865    Ljava/io/IOException;
        //  792    841    182    200    Ljava/net/SocketTimeoutException;
        //  792    841    285    321    Ljava/net/MalformedURLException;
        //  792    841    852    865    Ljava/io/IOException;
        //  844    852    182    200    Ljava/net/SocketTimeoutException;
        //  844    852    285    321    Ljava/net/MalformedURLException;
        //  844    852    852    865    Ljava/io/IOException;
        //  869    874    182    200    Ljava/net/SocketTimeoutException;
        //  869    874    285    321    Ljava/net/MalformedURLException;
        //  869    874    447    468    Ljava/io/IOException;
        //  889    909    182    200    Ljava/net/SocketTimeoutException;
        //  889    909    285    321    Ljava/net/MalformedURLException;
        //  889    909    852    865    Ljava/io/IOException;
        // 
        // The error that occurred was:
        // 
        // java.lang.IllegalStateException: Expression is linked from several locations: Label_0111:
        //     at com.strobel.decompiler.ast.Error.expressionLinkedFromMultipleLocations(Error.java:27)
        //     at com.strobel.decompiler.ast.AstOptimizer.mergeDisparateObjectInitializations(AstOptimizer.java:2596)
        //     at com.strobel.decompiler.ast.AstOptimizer.optimize(AstOptimizer.java:235)
        //     at com.strobel.decompiler.ast.AstOptimizer.optimize(AstOptimizer.java:42)
        //     at com.strobel.decompiler.languages.java.ast.AstMethodBodyBuilder.createMethodBody(AstMethodBodyBuilder.java:214)
        //     at com.strobel.decompiler.languages.java.ast.AstMethodBodyBuilder.createMethodBody(AstMethodBodyBuilder.java:99)
        //     at com.strobel.decompiler.languages.java.ast.AstBuilder.createMethodBody(AstBuilder.java:782)
        //     at com.strobel.decompiler.languages.java.ast.AstBuilder.createMethod(AstBuilder.java:675)
        //     at com.strobel.decompiler.languages.java.ast.AstBuilder.addTypeMembers(AstBuilder.java:552)
        //     at com.strobel.decompiler.languages.java.ast.AstBuilder.createTypeCore(AstBuilder.java:519)
        //     at com.strobel.decompiler.languages.java.ast.AstBuilder.createTypeNoCache(AstBuilder.java:161)
        //     at com.strobel.decompiler.languages.java.ast.AstBuilder.createType(AstBuilder.java:150)
        //     at com.strobel.decompiler.languages.java.ast.AstBuilder.addType(AstBuilder.java:125)
        //     at com.strobel.decompiler.languages.java.JavaLanguage.buildAst(JavaLanguage.java:71)
        //     at com.strobel.decompiler.languages.java.JavaLanguage.decompileType(JavaLanguage.java:59)
        //     at com.strobel.decompiler.DecompilerDriver.decompileType(DecompilerDriver.java:330)
        //     at com.strobel.decompiler.DecompilerDriver.decompileJar(DecompilerDriver.java:251)
        //     at com.strobel.decompiler.DecompilerDriver.main(DecompilerDriver.java:126)
        // 
        throw new IllegalStateException("An error occurred while decompiling this method.");
    }
}
