// 
// Decompiled by Procyon v0.5.34
// 

package com.google.android.gms.internal.ads;

import android.content.Intent;
import android.content.BroadcastReceiver;
import java.util.concurrent.ExecutionException;
import java.util.concurrent.TimeoutException;
import java.util.concurrent.TimeUnit;
import java.lang.reflect.Method;
import android.util.Log;
import android.support.annotation.VisibleForTesting;
import java.io.IOException;
import com.google.android.gms.common.GooglePlayServicesNotAvailableException;
import com.google.android.gms.common.GooglePlayServicesRepairableException;
import java.io.File;
import java.util.HashMap;
import android.util.Pair;
import java.util.Map;
import java.util.concurrent.Future;
import com.google.android.gms.ads.identifier.AdvertisingIdClient;
import dalvik.system.DexClassLoader;
import java.util.concurrent.ExecutorService;
import android.content.Context;

public class zzcz
{
    private static final String TAG;
    private volatile boolean zzqt;
    protected Context zzrt;
    private ExecutorService zzru;
    private DexClassLoader zzrv;
    private zzck zzrw;
    private byte[] zzrx;
    private volatile AdvertisingIdClient zzry;
    private Future zzrz;
    private boolean zzsa;
    private volatile zzba zzsb;
    private Future zzsc;
    private zzcc zzsd;
    private boolean zzse;
    private boolean zzsf;
    private Map<Pair<String, String>, zzeg> zzsg;
    private boolean zzsh;
    private boolean zzsi;
    private boolean zzsj;
    
    static {
        TAG = zzcz.class.getSimpleName();
    }
    
    private zzcz(Context zzrt) {
        boolean zzsa = true;
        this.zzry = null;
        this.zzqt = false;
        this.zzrz = null;
        this.zzsb = null;
        this.zzsc = null;
        this.zzse = false;
        this.zzsf = false;
        this.zzsh = false;
        this.zzsi = true;
        this.zzsj = false;
        final Context applicationContext = zzrt.getApplicationContext();
        if (applicationContext == null) {
            zzsa = false;
        }
        this.zzsa = zzsa;
        if (this.zzsa) {
            zzrt = applicationContext;
        }
        this.zzrt = zzrt;
        this.zzsg = new HashMap<Pair<String, String>, zzeg>();
    }
    
    public static zzcz zza(final Context p0, final String p1, final String p2, final boolean p3) {
        // 
        // This method could not be decompiled.
        // 
        // Original Bytecode:
        // 
        //     1: istore          4
        //     3: new             Lcom/google/android/gms/internal/ads/zzcz;
        //     6: dup            
        //     7: aload_0        
        //     8: invokespecial   com/google/android/gms/internal/ads/zzcz.<init>:(Landroid/content/Context;)V
        //    11: astore          5
        //    13: aload           5
        //    15: new             Lcom/google/android/gms/internal/ads/zzda;
        //    18: dup            
        //    19: invokespecial   com/google/android/gms/internal/ads/zzda.<init>:()V
        //    22: invokestatic    java/util/concurrent/Executors.newCachedThreadPool:(Ljava/util/concurrent/ThreadFactory;)Ljava/util/concurrent/ExecutorService;
        //    25: putfield        com/google/android/gms/internal/ads/zzcz.zzru:Ljava/util/concurrent/ExecutorService;
        //    28: aload           5
        //    30: iload_3        
        //    31: putfield        com/google/android/gms/internal/ads/zzcz.zzqt:Z
        //    34: iload_3        
        //    35: ifeq            62
        //    38: aload           5
        //    40: aload           5
        //    42: getfield        com/google/android/gms/internal/ads/zzcz.zzru:Ljava/util/concurrent/ExecutorService;
        //    45: new             Lcom/google/android/gms/internal/ads/zzdb;
        //    48: dup            
        //    49: aload           5
        //    51: invokespecial   com/google/android/gms/internal/ads/zzdb.<init>:(Lcom/google/android/gms/internal/ads/zzcz;)V
        //    54: invokeinterface java/util/concurrent/ExecutorService.submit:(Ljava/lang/Runnable;)Ljava/util/concurrent/Future;
        //    59: putfield        com/google/android/gms/internal/ads/zzcz.zzrz:Ljava/util/concurrent/Future;
        //    62: aload           5
        //    64: getfield        com/google/android/gms/internal/ads/zzcz.zzru:Ljava/util/concurrent/ExecutorService;
        //    67: new             Lcom/google/android/gms/internal/ads/zzdd;
        //    70: dup            
        //    71: aload           5
        //    73: invokespecial   com/google/android/gms/internal/ads/zzdd.<init>:(Lcom/google/android/gms/internal/ads/zzcz;)V
        //    76: invokeinterface java/util/concurrent/ExecutorService.execute:(Ljava/lang/Runnable;)V
        //    81: invokestatic    com/google/android/gms/common/GoogleApiAvailabilityLight.getInstance:()Lcom/google/android/gms/common/GoogleApiAvailabilityLight;
        //    84: astore_0       
        //    85: aload_0        
        //    86: aload           5
        //    88: getfield        com/google/android/gms/internal/ads/zzcz.zzrt:Landroid/content/Context;
        //    91: invokevirtual   com/google/android/gms/common/GoogleApiAvailabilityLight.getApkVersion:(Landroid/content/Context;)I
        //    94: ifle            560
        //    97: iconst_1       
        //    98: istore_3       
        //    99: aload           5
        //   101: iload_3        
        //   102: putfield        com/google/android/gms/internal/ads/zzcz.zzse:Z
        //   105: aload_0        
        //   106: aload           5
        //   108: getfield        com/google/android/gms/internal/ads/zzcz.zzrt:Landroid/content/Context;
        //   111: invokevirtual   com/google/android/gms/common/GoogleApiAvailabilityLight.isGooglePlayServicesAvailable:(Landroid/content/Context;)I
        //   114: ifne            565
        //   117: iload           4
        //   119: istore_3       
        //   120: aload           5
        //   122: iload_3        
        //   123: putfield        com/google/android/gms/internal/ads/zzcz.zzsf:Z
        //   126: aload           5
        //   128: iconst_0       
        //   129: iconst_1       
        //   130: invokevirtual   com/google/android/gms/internal/ads/zzcz.zza:(IZ)V
        //   133: invokestatic    com/google/android/gms/internal/ads/zzdg.isMainThread:()Z
        //   136: ifeq            169
        //   139: getstatic       com/google/android/gms/internal/ads/zznk.zzbaz:Lcom/google/android/gms/internal/ads/zzna;
        //   142: astore_0       
        //   143: invokestatic    com/google/android/gms/internal/ads/zzkb.zzik:()Lcom/google/android/gms/internal/ads/zzni;
        //   146: aload_0        
        //   147: invokevirtual   com/google/android/gms/internal/ads/zzni.zzd:(Lcom/google/android/gms/internal/ads/zzna;)Ljava/lang/Object;
        //   150: checkcast       Ljava/lang/Boolean;
        //   153: invokevirtual   java/lang/Boolean.booleanValue:()Z
        //   156: ifeq            169
        //   159: new             Ljava/lang/IllegalStateException;
        //   162: dup            
        //   163: ldc             "Task Context initialization must not be called from the UI thread."
        //   165: invokespecial   java/lang/IllegalStateException.<init>:(Ljava/lang/String;)V
        //   168: athrow         
        //   169: aload           5
        //   171: new             Lcom/google/android/gms/internal/ads/zzck;
        //   174: dup            
        //   175: aconst_null    
        //   176: invokespecial   com/google/android/gms/internal/ads/zzck.<init>:(Ljava/security/SecureRandom;)V
        //   179: putfield        com/google/android/gms/internal/ads/zzcz.zzrw:Lcom/google/android/gms/internal/ads/zzck;
        //   182: aload           5
        //   184: aload           5
        //   186: getfield        com/google/android/gms/internal/ads/zzcz.zzrw:Lcom/google/android/gms/internal/ads/zzck;
        //   189: aload_1        
        //   190: invokevirtual   com/google/android/gms/internal/ads/zzck.zzl:(Ljava/lang/String;)[B
        //   193: putfield        com/google/android/gms/internal/ads/zzcz.zzrx:[B
        //   196: aload           5
        //   198: getfield        com/google/android/gms/internal/ads/zzcz.zzrt:Landroid/content/Context;
        //   201: invokevirtual   android/content/Context.getCacheDir:()Ljava/io/File;
        //   204: astore_1       
        //   205: aload_1        
        //   206: astore_0       
        //   207: aload_1        
        //   208: ifnonnull       257
        //   211: aload           5
        //   213: getfield        com/google/android/gms/internal/ads/zzcz.zzrt:Landroid/content/Context;
        //   216: ldc             "dex"
        //   218: iconst_0       
        //   219: invokevirtual   android/content/Context.getDir:(Ljava/lang/String;I)Ljava/io/File;
        //   222: astore_1       
        //   223: aload_1        
        //   224: astore_0       
        //   225: aload_1        
        //   226: ifnonnull       257
        //   229: new             Lcom/google/android/gms/internal/ads/zzcw;
        //   232: dup            
        //   233: invokespecial   com/google/android/gms/internal/ads/zzcw.<init>:()V
        //   236: athrow         
        //   237: astore_0       
        //   238: new             Lcom/google/android/gms/internal/ads/zzcw;
        //   241: dup            
        //   242: aload_0        
        //   243: invokespecial   com/google/android/gms/internal/ads/zzcw.<init>:(Ljava/lang/Throwable;)V
        //   246: athrow         
        //   247: astore_0       
        //   248: new             Lcom/google/android/gms/internal/ads/zzcw;
        //   251: dup            
        //   252: aload_0        
        //   253: invokespecial   com/google/android/gms/internal/ads/zzcw.<init>:(Ljava/lang/Throwable;)V
        //   256: athrow         
        //   257: new             Ljava/io/File;
        //   260: dup            
        //   261: ldc             "%s/%s.jar"
        //   263: iconst_2       
        //   264: anewarray       Ljava/lang/Object;
        //   267: dup            
        //   268: iconst_0       
        //   269: aload_0        
        //   270: aastore        
        //   271: dup            
        //   272: iconst_1       
        //   273: ldc             "1521499837408"
        //   275: aastore        
        //   276: invokestatic    java/lang/String.format:(Ljava/lang/String;[Ljava/lang/Object;)Ljava/lang/String;
        //   279: invokespecial   java/io/File.<init>:(Ljava/lang/String;)V
        //   282: astore_1       
        //   283: aload_1        
        //   284: invokevirtual   java/io/File.exists:()Z
        //   287: ifne            334
        //   290: aload           5
        //   292: getfield        com/google/android/gms/internal/ads/zzcz.zzrw:Lcom/google/android/gms/internal/ads/zzck;
        //   295: aload           5
        //   297: getfield        com/google/android/gms/internal/ads/zzcz.zzrx:[B
        //   300: aload_2        
        //   301: invokevirtual   com/google/android/gms/internal/ads/zzck.zza:([BLjava/lang/String;)[B
        //   304: astore_2       
        //   305: aload_1        
        //   306: invokevirtual   java/io/File.createNewFile:()Z
        //   309: pop            
        //   310: new             Ljava/io/FileOutputStream;
        //   313: dup            
        //   314: aload_1        
        //   315: invokespecial   java/io/FileOutputStream.<init>:(Ljava/io/File;)V
        //   318: astore          6
        //   320: aload           6
        //   322: aload_2        
        //   323: iconst_0       
        //   324: aload_2        
        //   325: arraylength    
        //   326: invokevirtual   java/io/FileOutputStream.write:([BII)V
        //   329: aload           6
        //   331: invokevirtual   java/io/FileOutputStream.close:()V
        //   334: aload           5
        //   336: aload_0        
        //   337: ldc             "1521499837408"
        //   339: invokespecial   com/google/android/gms/internal/ads/zzcz.zzb:(Ljava/io/File;Ljava/lang/String;)Z
        //   342: pop            
        //   343: aload           5
        //   345: new             Ldalvik/system/DexClassLoader;
        //   348: dup            
        //   349: aload_1        
        //   350: invokevirtual   java/io/File.getAbsolutePath:()Ljava/lang/String;
        //   353: aload_0        
        //   354: invokevirtual   java/io/File.getAbsolutePath:()Ljava/lang/String;
        //   357: aconst_null    
        //   358: aload           5
        //   360: getfield        com/google/android/gms/internal/ads/zzcz.zzrt:Landroid/content/Context;
        //   363: invokevirtual   android/content/Context.getClassLoader:()Ljava/lang/ClassLoader;
        //   366: invokespecial   dalvik/system/DexClassLoader.<init>:(Ljava/lang/String;Ljava/lang/String;Ljava/lang/String;Ljava/lang/ClassLoader;)V
        //   369: putfield        com/google/android/gms/internal/ads/zzcz.zzrv:Ldalvik/system/DexClassLoader;
        //   372: aload_1        
        //   373: invokestatic    com/google/android/gms/internal/ads/zzcz.zzb:(Ljava/io/File;)V
        //   376: aload           5
        //   378: aload_0        
        //   379: ldc             "1521499837408"
        //   381: invokespecial   com/google/android/gms/internal/ads/zzcz.zza:(Ljava/io/File;Ljava/lang/String;)V
        //   384: ldc_w           "%s/%s.dex"
        //   387: iconst_2       
        //   388: anewarray       Ljava/lang/Object;
        //   391: dup            
        //   392: iconst_0       
        //   393: aload_0        
        //   394: aastore        
        //   395: dup            
        //   396: iconst_1       
        //   397: ldc             "1521499837408"
        //   399: aastore        
        //   400: invokestatic    java/lang/String.format:(Ljava/lang/String;[Ljava/lang/Object;)Ljava/lang/String;
        //   403: invokestatic    com/google/android/gms/internal/ads/zzcz.zzm:(Ljava/lang/String;)V
        //   406: aload           5
        //   408: getfield        com/google/android/gms/internal/ads/zzcz.zzsj:Z
        //   411: ifne            462
        //   414: new             Landroid/content/IntentFilter;
        //   417: dup            
        //   418: invokespecial   android/content/IntentFilter.<init>:()V
        //   421: astore_0       
        //   422: aload_0        
        //   423: ldc_w           "android.intent.action.USER_PRESENT"
        //   426: invokevirtual   android/content/IntentFilter.addAction:(Ljava/lang/String;)V
        //   429: aload_0        
        //   430: ldc_w           "android.intent.action.SCREEN_OFF"
        //   433: invokevirtual   android/content/IntentFilter.addAction:(Ljava/lang/String;)V
        //   436: aload           5
        //   438: getfield        com/google/android/gms/internal/ads/zzcz.zzrt:Landroid/content/Context;
        //   441: new             Lcom/google/android/gms/internal/ads/zzcz$zza;
        //   444: dup            
        //   445: aload           5
        //   447: aconst_null    
        //   448: invokespecial   com/google/android/gms/internal/ads/zzcz$zza.<init>:(Lcom/google/android/gms/internal/ads/zzcz;Lcom/google/android/gms/internal/ads/zzda;)V
        //   451: aload_0        
        //   452: invokevirtual   android/content/Context.registerReceiver:(Landroid/content/BroadcastReceiver;Landroid/content/IntentFilter;)Landroid/content/Intent;
        //   455: pop            
        //   456: aload           5
        //   458: iconst_1       
        //   459: putfield        com/google/android/gms/internal/ads/zzcz.zzsj:Z
        //   462: aload           5
        //   464: new             Lcom/google/android/gms/internal/ads/zzcc;
        //   467: dup            
        //   468: aload           5
        //   470: invokespecial   com/google/android/gms/internal/ads/zzcc.<init>:(Lcom/google/android/gms/internal/ads/zzcz;)V
        //   473: putfield        com/google/android/gms/internal/ads/zzcz.zzsd:Lcom/google/android/gms/internal/ads/zzcc;
        //   476: aload           5
        //   478: iconst_1       
        //   479: putfield        com/google/android/gms/internal/ads/zzcz.zzsh:Z
        //   482: aload           5
        //   484: areturn        
        //   485: astore_2       
        //   486: aload_1        
        //   487: invokestatic    com/google/android/gms/internal/ads/zzcz.zzb:(Ljava/io/File;)V
        //   490: aload           5
        //   492: aload_0        
        //   493: ldc             "1521499837408"
        //   495: invokespecial   com/google/android/gms/internal/ads/zzcz.zza:(Ljava/io/File;Ljava/lang/String;)V
        //   498: ldc_w           "%s/%s.dex"
        //   501: iconst_2       
        //   502: anewarray       Ljava/lang/Object;
        //   505: dup            
        //   506: iconst_0       
        //   507: aload_0        
        //   508: aastore        
        //   509: dup            
        //   510: iconst_1       
        //   511: ldc             "1521499837408"
        //   513: aastore        
        //   514: invokestatic    java/lang/String.format:(Ljava/lang/String;[Ljava/lang/Object;)Ljava/lang/String;
        //   517: invokestatic    com/google/android/gms/internal/ads/zzcz.zzm:(Ljava/lang/String;)V
        //   520: aload_2        
        //   521: athrow         
        //   522: astore_0       
        //   523: new             Lcom/google/android/gms/internal/ads/zzcw;
        //   526: dup            
        //   527: aload_0        
        //   528: invokespecial   com/google/android/gms/internal/ads/zzcw.<init>:(Ljava/lang/Throwable;)V
        //   531: athrow         
        //   532: astore_0       
        //   533: new             Lcom/google/android/gms/internal/ads/zzcw;
        //   536: dup            
        //   537: aload_0        
        //   538: invokespecial   com/google/android/gms/internal/ads/zzcw.<init>:(Ljava/lang/Throwable;)V
        //   541: athrow         
        //   542: astore_0       
        //   543: new             Lcom/google/android/gms/internal/ads/zzcw;
        //   546: dup            
        //   547: aload_0        
        //   548: invokespecial   com/google/android/gms/internal/ads/zzcw.<init>:(Ljava/lang/Throwable;)V
        //   551: athrow         
        //   552: astore_0       
        //   553: goto            126
        //   556: astore_0       
        //   557: aload           5
        //   559: areturn        
        //   560: iconst_0       
        //   561: istore_3       
        //   562: goto            99
        //   565: iconst_0       
        //   566: istore_3       
        //   567: goto            120
        //    Exceptions:
        //  Try           Handler
        //  Start  End    Start  End    Type                                      
        //  -----  -----  -----  -----  ------------------------------------------
        //  13     34     556    560    Lcom/google/android/gms/internal/ads/zzcw;
        //  38     62     556    560    Lcom/google/android/gms/internal/ads/zzcw;
        //  62     81     556    560    Lcom/google/android/gms/internal/ads/zzcw;
        //  81     97     552    556    Ljava/lang/Throwable;
        //  81     97     556    560    Lcom/google/android/gms/internal/ads/zzcw;
        //  99     117    552    556    Ljava/lang/Throwable;
        //  99     117    556    560    Lcom/google/android/gms/internal/ads/zzcw;
        //  120    126    552    556    Ljava/lang/Throwable;
        //  120    126    556    560    Lcom/google/android/gms/internal/ads/zzcw;
        //  126    169    556    560    Lcom/google/android/gms/internal/ads/zzcw;
        //  169    182    556    560    Lcom/google/android/gms/internal/ads/zzcw;
        //  182    196    247    257    Lcom/google/android/gms/internal/ads/zzcl;
        //  182    196    556    560    Lcom/google/android/gms/internal/ads/zzcw;
        //  196    205    237    247    Ljava/io/FileNotFoundException;
        //  196    205    522    532    Ljava/io/IOException;
        //  196    205    532    542    Lcom/google/android/gms/internal/ads/zzcl;
        //  196    205    542    552    Ljava/lang/NullPointerException;
        //  196    205    556    560    Lcom/google/android/gms/internal/ads/zzcw;
        //  211    223    237    247    Ljava/io/FileNotFoundException;
        //  211    223    522    532    Ljava/io/IOException;
        //  211    223    532    542    Lcom/google/android/gms/internal/ads/zzcl;
        //  211    223    542    552    Ljava/lang/NullPointerException;
        //  211    223    556    560    Lcom/google/android/gms/internal/ads/zzcw;
        //  229    237    237    247    Ljava/io/FileNotFoundException;
        //  229    237    522    532    Ljava/io/IOException;
        //  229    237    532    542    Lcom/google/android/gms/internal/ads/zzcl;
        //  229    237    542    552    Ljava/lang/NullPointerException;
        //  229    237    556    560    Lcom/google/android/gms/internal/ads/zzcw;
        //  238    247    556    560    Lcom/google/android/gms/internal/ads/zzcw;
        //  248    257    556    560    Lcom/google/android/gms/internal/ads/zzcw;
        //  257    334    237    247    Ljava/io/FileNotFoundException;
        //  257    334    522    532    Ljava/io/IOException;
        //  257    334    532    542    Lcom/google/android/gms/internal/ads/zzcl;
        //  257    334    542    552    Ljava/lang/NullPointerException;
        //  257    334    556    560    Lcom/google/android/gms/internal/ads/zzcw;
        //  334    343    237    247    Ljava/io/FileNotFoundException;
        //  334    343    522    532    Ljava/io/IOException;
        //  334    343    532    542    Lcom/google/android/gms/internal/ads/zzcl;
        //  334    343    542    552    Ljava/lang/NullPointerException;
        //  334    343    556    560    Lcom/google/android/gms/internal/ads/zzcw;
        //  343    372    485    522    Any
        //  372    406    237    247    Ljava/io/FileNotFoundException;
        //  372    406    522    532    Ljava/io/IOException;
        //  372    406    532    542    Lcom/google/android/gms/internal/ads/zzcl;
        //  372    406    542    552    Ljava/lang/NullPointerException;
        //  372    406    556    560    Lcom/google/android/gms/internal/ads/zzcw;
        //  406    462    556    560    Lcom/google/android/gms/internal/ads/zzcw;
        //  462    482    556    560    Lcom/google/android/gms/internal/ads/zzcw;
        //  486    522    237    247    Ljava/io/FileNotFoundException;
        //  486    522    522    532    Ljava/io/IOException;
        //  486    522    532    542    Lcom/google/android/gms/internal/ads/zzcl;
        //  486    522    542    552    Ljava/lang/NullPointerException;
        //  486    522    556    560    Lcom/google/android/gms/internal/ads/zzcw;
        //  523    532    556    560    Lcom/google/android/gms/internal/ads/zzcw;
        //  533    542    556    560    Lcom/google/android/gms/internal/ads/zzcw;
        //  543    552    556    560    Lcom/google/android/gms/internal/ads/zzcw;
        // 
        // The error that occurred was:
        // 
        // java.lang.IllegalStateException: Expression is linked from several locations: Label_0462:
        //     at com.strobel.decompiler.ast.Error.expressionLinkedFromMultipleLocations(Error.java:27)
        //     at com.strobel.decompiler.ast.AstOptimizer.mergeDisparateObjectInitializations(AstOptimizer.java:2596)
        //     at com.strobel.decompiler.ast.AstOptimizer.optimize(AstOptimizer.java:235)
        //     at com.strobel.decompiler.ast.AstOptimizer.optimize(AstOptimizer.java:42)
        //     at com.strobel.decompiler.languages.java.ast.AstMethodBodyBuilder.createMethodBody(AstMethodBodyBuilder.java:214)
        //     at com.strobel.decompiler.languages.java.ast.AstMethodBodyBuilder.createMethodBody(AstMethodBodyBuilder.java:99)
        //     at com.strobel.decompiler.languages.java.ast.AstBuilder.createMethodBody(AstBuilder.java:782)
        //     at com.strobel.decompiler.languages.java.ast.AstBuilder.createMethod(AstBuilder.java:675)
        //     at com.strobel.decompiler.languages.java.ast.AstBuilder.addTypeMembers(AstBuilder.java:552)
        //     at com.strobel.decompiler.languages.java.ast.AstBuilder.createTypeCore(AstBuilder.java:519)
        //     at com.strobel.decompiler.languages.java.ast.AstBuilder.createTypeNoCache(AstBuilder.java:161)
        //     at com.strobel.decompiler.languages.java.ast.AstBuilder.createType(AstBuilder.java:150)
        //     at com.strobel.decompiler.languages.java.ast.AstBuilder.addType(AstBuilder.java:125)
        //     at com.strobel.decompiler.languages.java.JavaLanguage.buildAst(JavaLanguage.java:71)
        //     at com.strobel.decompiler.languages.java.JavaLanguage.decompileType(JavaLanguage.java:59)
        //     at com.strobel.decompiler.DecompilerDriver.decompileType(DecompilerDriver.java:330)
        //     at com.strobel.decompiler.DecompilerDriver.decompileJar(DecompilerDriver.java:251)
        //     at com.strobel.decompiler.DecompilerDriver.main(DecompilerDriver.java:126)
        // 
        throw new IllegalStateException("An error occurred while decompiling this method.");
    }
    
    private final void zza(final File p0, final String p1) {
        // 
        // This method could not be decompiled.
        // 
        // Original Bytecode:
        // 
        //     1: astore          6
        //     3: aconst_null    
        //     4: astore          7
        //     6: new             Ljava/io/File;
        //     9: dup            
        //    10: ldc_w           "%s/%s.tmp"
        //    13: iconst_2       
        //    14: anewarray       Ljava/lang/Object;
        //    17: dup            
        //    18: iconst_0       
        //    19: aload_1        
        //    20: aastore        
        //    21: dup            
        //    22: iconst_1       
        //    23: aload_2        
        //    24: aastore        
        //    25: invokestatic    java/lang/String.format:(Ljava/lang/String;[Ljava/lang/Object;)Ljava/lang/String;
        //    28: invokespecial   java/io/File.<init>:(Ljava/lang/String;)V
        //    31: astore          9
        //    33: aload           9
        //    35: invokevirtual   java/io/File.exists:()Z
        //    38: ifeq            42
        //    41: return         
        //    42: new             Ljava/io/File;
        //    45: dup            
        //    46: ldc_w           "%s/%s.dex"
        //    49: iconst_2       
        //    50: anewarray       Ljava/lang/Object;
        //    53: dup            
        //    54: iconst_0       
        //    55: aload_1        
        //    56: aastore        
        //    57: dup            
        //    58: iconst_1       
        //    59: aload_2        
        //    60: aastore        
        //    61: invokestatic    java/lang/String.format:(Ljava/lang/String;[Ljava/lang/Object;)Ljava/lang/String;
        //    64: invokespecial   java/io/File.<init>:(Ljava/lang/String;)V
        //    67: astore          8
        //    69: aload           8
        //    71: invokevirtual   java/io/File.exists:()Z
        //    74: ifeq            41
        //    77: aload           8
        //    79: invokevirtual   java/io/File.length:()J
        //    82: lstore          4
        //    84: lload           4
        //    86: lconst_0       
        //    87: lcmp           
        //    88: ifle            41
        //    91: lload           4
        //    93: l2i            
        //    94: newarray        B
        //    96: astore          10
        //    98: new             Ljava/io/FileInputStream;
        //   101: dup            
        //   102: aload           8
        //   104: invokespecial   java/io/FileInputStream.<init>:(Ljava/io/File;)V
        //   107: astore_1       
        //   108: aload_1        
        //   109: aload           10
        //   111: invokevirtual   java/io/FileInputStream.read:([B)I
        //   114: istore_3       
        //   115: iload_3        
        //   116: ifgt            129
        //   119: aload_1        
        //   120: invokevirtual   java/io/FileInputStream.close:()V
        //   123: aload           8
        //   125: invokestatic    com/google/android/gms/internal/ads/zzcz.zzb:(Ljava/io/File;)V
        //   128: return         
        //   129: new             Lcom/google/android/gms/internal/ads/zzbe;
        //   132: dup            
        //   133: invokespecial   com/google/android/gms/internal/ads/zzbe.<init>:()V
        //   136: astore          7
        //   138: aload           7
        //   140: getstatic       android/os/Build$VERSION.SDK:Ljava/lang/String;
        //   143: invokevirtual   java/lang/String.getBytes:()[B
        //   146: putfield        com/google/android/gms/internal/ads/zzbe.zzgs:[B
        //   149: aload           7
        //   151: aload_2        
        //   152: invokevirtual   java/lang/String.getBytes:()[B
        //   155: putfield        com/google/android/gms/internal/ads/zzbe.zzgr:[B
        //   158: aload_0        
        //   159: getfield        com/google/android/gms/internal/ads/zzcz.zzrw:Lcom/google/android/gms/internal/ads/zzck;
        //   162: aload_0        
        //   163: getfield        com/google/android/gms/internal/ads/zzcz.zzrx:[B
        //   166: aload           10
        //   168: invokevirtual   com/google/android/gms/internal/ads/zzck.zzb:([B[B)Ljava/lang/String;
        //   171: invokevirtual   java/lang/String.getBytes:()[B
        //   174: astore_2       
        //   175: aload           7
        //   177: aload_2        
        //   178: putfield        com/google/android/gms/internal/ads/zzbe.data:[B
        //   181: aload           7
        //   183: aload_2        
        //   184: invokestatic    com/google/android/gms/internal/ads/zzbk.zzb:([B)[B
        //   187: putfield        com/google/android/gms/internal/ads/zzbe.zzgq:[B
        //   190: aload           9
        //   192: invokevirtual   java/io/File.createNewFile:()Z
        //   195: pop            
        //   196: new             Ljava/io/FileOutputStream;
        //   199: dup            
        //   200: aload           9
        //   202: invokespecial   java/io/FileOutputStream.<init>:(Ljava/io/File;)V
        //   205: astore_2       
        //   206: aload           7
        //   208: invokestatic    com/google/android/gms/internal/ads/zzbfi.zzb:(Lcom/google/android/gms/internal/ads/zzbfi;)[B
        //   211: astore          6
        //   213: aload_2        
        //   214: aload           6
        //   216: iconst_0       
        //   217: aload           6
        //   219: arraylength    
        //   220: invokevirtual   java/io/FileOutputStream.write:([BII)V
        //   223: aload_2        
        //   224: invokevirtual   java/io/FileOutputStream.close:()V
        //   227: aload_1        
        //   228: invokevirtual   java/io/FileInputStream.close:()V
        //   231: aload_2        
        //   232: invokevirtual   java/io/FileOutputStream.close:()V
        //   235: aload           8
        //   237: invokestatic    com/google/android/gms/internal/ads/zzcz.zzb:(Ljava/io/File;)V
        //   240: return         
        //   241: astore_1       
        //   242: aconst_null    
        //   243: astore_1       
        //   244: aload           7
        //   246: astore_2       
        //   247: aload_2        
        //   248: ifnull          255
        //   251: aload_2        
        //   252: invokevirtual   java/io/FileInputStream.close:()V
        //   255: aload_1        
        //   256: ifnull          263
        //   259: aload_1        
        //   260: invokevirtual   java/io/FileOutputStream.close:()V
        //   263: aload           8
        //   265: invokestatic    com/google/android/gms/internal/ads/zzcz.zzb:(Ljava/io/File;)V
        //   268: return         
        //   269: astore_2       
        //   270: aconst_null    
        //   271: astore_1       
        //   272: aload_1        
        //   273: ifnull          280
        //   276: aload_1        
        //   277: invokevirtual   java/io/FileInputStream.close:()V
        //   280: aload           6
        //   282: ifnull          290
        //   285: aload           6
        //   287: invokevirtual   java/io/FileOutputStream.close:()V
        //   290: aload           8
        //   292: invokestatic    com/google/android/gms/internal/ads/zzcz.zzb:(Ljava/io/File;)V
        //   295: aload_2        
        //   296: athrow         
        //   297: astore_1       
        //   298: goto            123
        //   301: astore_1       
        //   302: goto            231
        //   305: astore_1       
        //   306: goto            235
        //   309: astore_2       
        //   310: goto            255
        //   313: astore_1       
        //   314: goto            263
        //   317: astore_1       
        //   318: goto            280
        //   321: astore_1       
        //   322: goto            290
        //   325: astore_2       
        //   326: goto            272
        //   329: astore          7
        //   331: aload_2        
        //   332: astore          6
        //   334: aload           7
        //   336: astore_2       
        //   337: goto            272
        //   340: astore_2       
        //   341: aconst_null    
        //   342: astore          6
        //   344: aload_1        
        //   345: astore_2       
        //   346: aload           6
        //   348: astore_1       
        //   349: goto            247
        //   352: astore          6
        //   354: aload_1        
        //   355: astore          6
        //   357: aload_2        
        //   358: astore_1       
        //   359: aload           6
        //   361: astore_2       
        //   362: goto            247
        //   365: astore_1       
        //   366: aconst_null    
        //   367: astore_1       
        //   368: aload           7
        //   370: astore_2       
        //   371: goto            247
        //   374: astore_2       
        //   375: aconst_null    
        //   376: astore          6
        //   378: aload_1        
        //   379: astore_2       
        //   380: aload           6
        //   382: astore_1       
        //   383: goto            247
        //   386: astore          6
        //   388: aload_1        
        //   389: astore          6
        //   391: aload_2        
        //   392: astore_1       
        //   393: aload           6
        //   395: astore_2       
        //   396: goto            247
        //   399: astore_1       
        //   400: aconst_null    
        //   401: astore_1       
        //   402: aload           7
        //   404: astore_2       
        //   405: goto            247
        //   408: astore_2       
        //   409: aconst_null    
        //   410: astore          6
        //   412: aload_1        
        //   413: astore_2       
        //   414: aload           6
        //   416: astore_1       
        //   417: goto            247
        //   420: astore          6
        //   422: aload_1        
        //   423: astore          6
        //   425: aload_2        
        //   426: astore_1       
        //   427: aload           6
        //   429: astore_2       
        //   430: goto            247
        //    Exceptions:
        //  Try           Handler
        //  Start  End    Start  End    Type                                      
        //  -----  -----  -----  -----  ------------------------------------------
        //  98     108    365    374    Ljava/io/IOException;
        //  98     108    241    247    Ljava/security/NoSuchAlgorithmException;
        //  98     108    399    408    Lcom/google/android/gms/internal/ads/zzcl;
        //  98     108    269    272    Any
        //  108    115    374    386    Ljava/io/IOException;
        //  108    115    340    352    Ljava/security/NoSuchAlgorithmException;
        //  108    115    408    420    Lcom/google/android/gms/internal/ads/zzcl;
        //  108    115    325    329    Any
        //  119    123    297    301    Ljava/io/IOException;
        //  129    206    374    386    Ljava/io/IOException;
        //  129    206    340    352    Ljava/security/NoSuchAlgorithmException;
        //  129    206    408    420    Lcom/google/android/gms/internal/ads/zzcl;
        //  129    206    325    329    Any
        //  206    227    386    399    Ljava/io/IOException;
        //  206    227    352    365    Ljava/security/NoSuchAlgorithmException;
        //  206    227    420    433    Lcom/google/android/gms/internal/ads/zzcl;
        //  206    227    329    340    Any
        //  227    231    301    305    Ljava/io/IOException;
        //  231    235    305    309    Ljava/io/IOException;
        //  251    255    309    313    Ljava/io/IOException;
        //  259    263    313    317    Ljava/io/IOException;
        //  276    280    317    321    Ljava/io/IOException;
        //  285    290    321    325    Ljava/io/IOException;
        // 
        // The error that occurred was:
        // 
        // java.lang.IndexOutOfBoundsException: Index: 236, Size: 236
        //     at java.util.ArrayList.rangeCheck(ArrayList.java:653)
        //     at java.util.ArrayList.get(ArrayList.java:429)
        //     at com.strobel.decompiler.ast.AstBuilder.convertToAst(AstBuilder.java:3321)
        //     at com.strobel.decompiler.ast.AstBuilder.convertToAst(AstBuilder.java:3435)
        //     at com.strobel.decompiler.ast.AstBuilder.build(AstBuilder.java:113)
        //     at com.strobel.decompiler.languages.java.ast.AstMethodBodyBuilder.createMethodBody(AstMethodBodyBuilder.java:211)
        //     at com.strobel.decompiler.languages.java.ast.AstMethodBodyBuilder.createMethodBody(AstMethodBodyBuilder.java:99)
        //     at com.strobel.decompiler.languages.java.ast.AstBuilder.createMethodBody(AstBuilder.java:782)
        //     at com.strobel.decompiler.languages.java.ast.AstBuilder.createMethod(AstBuilder.java:675)
        //     at com.strobel.decompiler.languages.java.ast.AstBuilder.addTypeMembers(AstBuilder.java:552)
        //     at com.strobel.decompiler.languages.java.ast.AstBuilder.createTypeCore(AstBuilder.java:519)
        //     at com.strobel.decompiler.languages.java.ast.AstBuilder.createTypeNoCache(AstBuilder.java:161)
        //     at com.strobel.decompiler.languages.java.ast.AstBuilder.createType(AstBuilder.java:150)
        //     at com.strobel.decompiler.languages.java.ast.AstBuilder.addType(AstBuilder.java:125)
        //     at com.strobel.decompiler.languages.java.JavaLanguage.buildAst(JavaLanguage.java:71)
        //     at com.strobel.decompiler.languages.java.JavaLanguage.decompileType(JavaLanguage.java:59)
        //     at com.strobel.decompiler.DecompilerDriver.decompileType(DecompilerDriver.java:330)
        //     at com.strobel.decompiler.DecompilerDriver.decompileJar(DecompilerDriver.java:251)
        //     at com.strobel.decompiler.DecompilerDriver.main(DecompilerDriver.java:126)
        // 
        throw new IllegalStateException("An error occurred while decompiling this method.");
    }
    
    private static boolean zza(final int n, final zzba zzba) {
        if (n < 4) {
            if (zzba == null) {
                return true;
            }
            if ((boolean)zzkb.zzik().zzd(zznk.zzbbc) && (zzba.zzcx == null || zzba.zzcx.equals("0000000000000000000000000000000000000000000000000000000000000000"))) {
                return true;
            }
            if ((boolean)zzkb.zzik().zzd(zznk.zzbbd) && (zzba.zzfn == null || zzba.zzfn.zzgl == null || zzba.zzfn.zzgl == -2L)) {
                return true;
            }
        }
        return false;
    }
    
    private final void zzal() {
        try {
            if (this.zzry == null && this.zzsa) {
                final AdvertisingIdClient zzry = new AdvertisingIdClient(this.zzrt);
                zzry.start();
                this.zzry = zzry;
            }
        }
        catch (GooglePlayServicesRepairableException ex) {}
        catch (GooglePlayServicesNotAvailableException ex2) {
            goto Label_0037;
        }
        catch (IOException ex3) {
            goto Label_0037;
        }
    }
    
    @VisibleForTesting
    private final zzba zzam() {
        try {
            return zzatq.zzl(this.zzrt, this.zzrt.getPackageName(), Integer.toString(this.zzrt.getPackageManager().getPackageInfo(this.zzrt.getPackageName(), 0).versionCode));
        }
        catch (Throwable t) {
            return null;
        }
    }
    
    private static void zzb(final File file) {
        if (!file.exists()) {
            Log.d(zzcz.TAG, String.format("File %s not found. No need for deletion", file.getAbsolutePath()));
            return;
        }
        file.delete();
    }
    
    private final boolean zzb(final File p0, final String p1) {
        // 
        // This method could not be decompiled.
        // 
        // Original Bytecode:
        // 
        //     1: astore          5
        //     3: new             Ljava/io/File;
        //     6: dup            
        //     7: ldc_w           "%s/%s.tmp"
        //    10: iconst_2       
        //    11: anewarray       Ljava/lang/Object;
        //    14: dup            
        //    15: iconst_0       
        //    16: aload_1        
        //    17: aastore        
        //    18: dup            
        //    19: iconst_1       
        //    20: aload_2        
        //    21: aastore        
        //    22: invokestatic    java/lang/String.format:(Ljava/lang/String;[Ljava/lang/Object;)Ljava/lang/String;
        //    25: invokespecial   java/io/File.<init>:(Ljava/lang/String;)V
        //    28: astore          6
        //    30: aload           6
        //    32: invokevirtual   java/io/File.exists:()Z
        //    35: ifne            40
        //    38: iconst_0       
        //    39: ireturn        
        //    40: new             Ljava/io/File;
        //    43: dup            
        //    44: ldc_w           "%s/%s.dex"
        //    47: iconst_2       
        //    48: anewarray       Ljava/lang/Object;
        //    51: dup            
        //    52: iconst_0       
        //    53: aload_1        
        //    54: aastore        
        //    55: dup            
        //    56: iconst_1       
        //    57: aload_2        
        //    58: aastore        
        //    59: invokestatic    java/lang/String.format:(Ljava/lang/String;[Ljava/lang/Object;)Ljava/lang/String;
        //    62: invokespecial   java/io/File.<init>:(Ljava/lang/String;)V
        //    65: astore          7
        //    67: aload           7
        //    69: invokevirtual   java/io/File.exists:()Z
        //    72: ifeq            77
        //    75: iconst_0       
        //    76: ireturn        
        //    77: aload           6
        //    79: invokevirtual   java/io/File.length:()J
        //    82: lstore_3       
        //    83: lload_3        
        //    84: lconst_0       
        //    85: lcmp           
        //    86: ifgt            96
        //    89: aload           6
        //    91: invokestatic    com/google/android/gms/internal/ads/zzcz.zzb:(Ljava/io/File;)V
        //    94: iconst_0       
        //    95: ireturn        
        //    96: lload_3        
        //    97: l2i            
        //    98: newarray        B
        //   100: astore          8
        //   102: new             Ljava/io/FileInputStream;
        //   105: dup            
        //   106: aload           6
        //   108: invokespecial   java/io/FileInputStream.<init>:(Ljava/io/File;)V
        //   111: astore_1       
        //   112: aload_1        
        //   113: aload           8
        //   115: invokevirtual   java/io/FileInputStream.read:([B)I
        //   118: ifgt            142
        //   121: getstatic       com/google/android/gms/internal/ads/zzcz.TAG:Ljava/lang/String;
        //   124: ldc_w           "Cannot read the cache data."
        //   127: invokestatic    android/util/Log.d:(Ljava/lang/String;Ljava/lang/String;)I
        //   130: pop            
        //   131: aload           6
        //   133: invokestatic    com/google/android/gms/internal/ads/zzcz.zzb:(Ljava/io/File;)V
        //   136: aload_1        
        //   137: invokevirtual   java/io/FileInputStream.close:()V
        //   140: iconst_0       
        //   141: ireturn        
        //   142: new             Lcom/google/android/gms/internal/ads/zzbe;
        //   145: dup            
        //   146: invokespecial   com/google/android/gms/internal/ads/zzbe.<init>:()V
        //   149: aload           8
        //   151: invokestatic    com/google/android/gms/internal/ads/zzbfi.zza:(Lcom/google/android/gms/internal/ads/zzbfi;[B)Lcom/google/android/gms/internal/ads/zzbfi;
        //   154: checkcast       Lcom/google/android/gms/internal/ads/zzbe;
        //   157: astore          8
        //   159: aload_2        
        //   160: new             Ljava/lang/String;
        //   163: dup            
        //   164: aload           8
        //   166: getfield        com/google/android/gms/internal/ads/zzbe.zzgr:[B
        //   169: invokespecial   java/lang/String.<init>:([B)V
        //   172: invokevirtual   java/lang/String.equals:(Ljava/lang/Object;)Z
        //   175: ifeq            214
        //   178: aload           8
        //   180: getfield        com/google/android/gms/internal/ads/zzbe.zzgq:[B
        //   183: aload           8
        //   185: getfield        com/google/android/gms/internal/ads/zzbe.data:[B
        //   188: invokestatic    com/google/android/gms/internal/ads/zzbk.zzb:([B)[B
        //   191: invokestatic    java/util/Arrays.equals:([B[B)Z
        //   194: ifeq            214
        //   197: aload           8
        //   199: getfield        com/google/android/gms/internal/ads/zzbe.zzgs:[B
        //   202: getstatic       android/os/Build$VERSION.SDK:Ljava/lang/String;
        //   205: invokevirtual   java/lang/String.getBytes:()[B
        //   208: invokestatic    java/util/Arrays.equals:([B[B)Z
        //   211: ifne            225
        //   214: aload           6
        //   216: invokestatic    com/google/android/gms/internal/ads/zzcz.zzb:(Ljava/io/File;)V
        //   219: aload_1        
        //   220: invokevirtual   java/io/FileInputStream.close:()V
        //   223: iconst_0       
        //   224: ireturn        
        //   225: aload_0        
        //   226: getfield        com/google/android/gms/internal/ads/zzcz.zzrw:Lcom/google/android/gms/internal/ads/zzck;
        //   229: aload_0        
        //   230: getfield        com/google/android/gms/internal/ads/zzcz.zzrx:[B
        //   233: new             Ljava/lang/String;
        //   236: dup            
        //   237: aload           8
        //   239: getfield        com/google/android/gms/internal/ads/zzbe.data:[B
        //   242: invokespecial   java/lang/String.<init>:([B)V
        //   245: invokevirtual   com/google/android/gms/internal/ads/zzck.zza:([BLjava/lang/String;)[B
        //   248: astore          6
        //   250: aload           7
        //   252: invokevirtual   java/io/File.createNewFile:()Z
        //   255: pop            
        //   256: new             Ljava/io/FileOutputStream;
        //   259: dup            
        //   260: aload           7
        //   262: invokespecial   java/io/FileOutputStream.<init>:(Ljava/io/File;)V
        //   265: astore_2       
        //   266: aload_2        
        //   267: aload           6
        //   269: iconst_0       
        //   270: aload           6
        //   272: arraylength    
        //   273: invokevirtual   java/io/FileOutputStream.write:([BII)V
        //   276: aload_1        
        //   277: invokevirtual   java/io/FileInputStream.close:()V
        //   280: aload_2        
        //   281: invokevirtual   java/io/FileOutputStream.close:()V
        //   284: iconst_1       
        //   285: ireturn        
        //   286: astore_1       
        //   287: aconst_null    
        //   288: astore_2       
        //   289: aconst_null    
        //   290: astore_1       
        //   291: aload_1        
        //   292: ifnull          299
        //   295: aload_1        
        //   296: invokevirtual   java/io/FileInputStream.close:()V
        //   299: aload_2        
        //   300: ifnull          307
        //   303: aload_2        
        //   304: invokevirtual   java/io/FileOutputStream.close:()V
        //   307: iconst_0       
        //   308: ireturn        
        //   309: astore_2       
        //   310: aconst_null    
        //   311: astore_1       
        //   312: aload_1        
        //   313: ifnull          320
        //   316: aload_1        
        //   317: invokevirtual   java/io/FileInputStream.close:()V
        //   320: aload           5
        //   322: ifnull          330
        //   325: aload           5
        //   327: invokevirtual   java/io/FileOutputStream.close:()V
        //   330: aload_2        
        //   331: athrow         
        //   332: astore_1       
        //   333: goto            140
        //   336: astore_1       
        //   337: goto            223
        //   340: astore_1       
        //   341: goto            280
        //   344: astore_1       
        //   345: goto            284
        //   348: astore_1       
        //   349: goto            299
        //   352: astore_1       
        //   353: goto            307
        //   356: astore_1       
        //   357: goto            320
        //   360: astore_1       
        //   361: goto            330
        //   364: astore_2       
        //   365: goto            312
        //   368: astore          6
        //   370: aload_2        
        //   371: astore          5
        //   373: aload           6
        //   375: astore_2       
        //   376: goto            312
        //   379: astore_2       
        //   380: aconst_null    
        //   381: astore_2       
        //   382: goto            291
        //   385: astore          5
        //   387: goto            291
        //   390: astore_1       
        //   391: aconst_null    
        //   392: astore_2       
        //   393: aconst_null    
        //   394: astore_1       
        //   395: goto            291
        //   398: astore_2       
        //   399: aconst_null    
        //   400: astore_2       
        //   401: goto            291
        //   404: astore          5
        //   406: goto            291
        //   409: astore_1       
        //   410: aconst_null    
        //   411: astore_2       
        //   412: aconst_null    
        //   413: astore_1       
        //   414: goto            291
        //   417: astore_2       
        //   418: aconst_null    
        //   419: astore_2       
        //   420: goto            291
        //   423: astore          5
        //   425: goto            291
        //    Exceptions:
        //  Try           Handler
        //  Start  End    Start  End    Type                                      
        //  -----  -----  -----  -----  ------------------------------------------
        //  77     83     390    398    Ljava/io/IOException;
        //  77     83     286    291    Ljava/security/NoSuchAlgorithmException;
        //  77     83     409    417    Lcom/google/android/gms/internal/ads/zzcl;
        //  77     83     309    312    Any
        //  89     94     390    398    Ljava/io/IOException;
        //  89     94     286    291    Ljava/security/NoSuchAlgorithmException;
        //  89     94     409    417    Lcom/google/android/gms/internal/ads/zzcl;
        //  89     94     309    312    Any
        //  96     112    390    398    Ljava/io/IOException;
        //  96     112    286    291    Ljava/security/NoSuchAlgorithmException;
        //  96     112    409    417    Lcom/google/android/gms/internal/ads/zzcl;
        //  96     112    309    312    Any
        //  112    136    398    404    Ljava/io/IOException;
        //  112    136    379    385    Ljava/security/NoSuchAlgorithmException;
        //  112    136    417    423    Lcom/google/android/gms/internal/ads/zzcl;
        //  112    136    364    368    Any
        //  136    140    332    336    Ljava/io/IOException;
        //  142    214    398    404    Ljava/io/IOException;
        //  142    214    379    385    Ljava/security/NoSuchAlgorithmException;
        //  142    214    417    423    Lcom/google/android/gms/internal/ads/zzcl;
        //  142    214    364    368    Any
        //  214    219    398    404    Ljava/io/IOException;
        //  214    219    379    385    Ljava/security/NoSuchAlgorithmException;
        //  214    219    417    423    Lcom/google/android/gms/internal/ads/zzcl;
        //  214    219    364    368    Any
        //  219    223    336    340    Ljava/io/IOException;
        //  225    266    398    404    Ljava/io/IOException;
        //  225    266    379    385    Ljava/security/NoSuchAlgorithmException;
        //  225    266    417    423    Lcom/google/android/gms/internal/ads/zzcl;
        //  225    266    364    368    Any
        //  266    276    404    409    Ljava/io/IOException;
        //  266    276    385    390    Ljava/security/NoSuchAlgorithmException;
        //  266    276    423    428    Lcom/google/android/gms/internal/ads/zzcl;
        //  266    276    368    379    Any
        //  276    280    340    344    Ljava/io/IOException;
        //  280    284    344    348    Ljava/io/IOException;
        //  295    299    348    352    Ljava/io/IOException;
        //  303    307    352    356    Ljava/io/IOException;
        //  316    320    356    360    Ljava/io/IOException;
        //  325    330    360    364    Ljava/io/IOException;
        // 
        // The error that occurred was:
        // 
        // java.lang.IndexOutOfBoundsException: Index: 225, Size: 225
        //     at java.util.ArrayList.rangeCheck(ArrayList.java:653)
        //     at java.util.ArrayList.get(ArrayList.java:429)
        //     at com.strobel.decompiler.ast.AstBuilder.convertToAst(AstBuilder.java:3321)
        //     at com.strobel.decompiler.ast.AstBuilder.convertToAst(AstBuilder.java:3435)
        //     at com.strobel.decompiler.ast.AstBuilder.build(AstBuilder.java:113)
        //     at com.strobel.decompiler.languages.java.ast.AstMethodBodyBuilder.createMethodBody(AstMethodBodyBuilder.java:211)
        //     at com.strobel.decompiler.languages.java.ast.AstMethodBodyBuilder.createMethodBody(AstMethodBodyBuilder.java:99)
        //     at com.strobel.decompiler.languages.java.ast.AstBuilder.createMethodBody(AstBuilder.java:782)
        //     at com.strobel.decompiler.languages.java.ast.AstBuilder.createMethod(AstBuilder.java:675)
        //     at com.strobel.decompiler.languages.java.ast.AstBuilder.addTypeMembers(AstBuilder.java:552)
        //     at com.strobel.decompiler.languages.java.ast.AstBuilder.createTypeCore(AstBuilder.java:519)
        //     at com.strobel.decompiler.languages.java.ast.AstBuilder.createTypeNoCache(AstBuilder.java:161)
        //     at com.strobel.decompiler.languages.java.ast.AstBuilder.createType(AstBuilder.java:150)
        //     at com.strobel.decompiler.languages.java.ast.AstBuilder.addType(AstBuilder.java:125)
        //     at com.strobel.decompiler.languages.java.JavaLanguage.buildAst(JavaLanguage.java:71)
        //     at com.strobel.decompiler.languages.java.JavaLanguage.decompileType(JavaLanguage.java:59)
        //     at com.strobel.decompiler.DecompilerDriver.decompileType(DecompilerDriver.java:330)
        //     at com.strobel.decompiler.DecompilerDriver.decompileJar(DecompilerDriver.java:251)
        //     at com.strobel.decompiler.DecompilerDriver.main(DecompilerDriver.java:126)
        // 
        throw new IllegalStateException("An error occurred while decompiling this method.");
    }
    
    private static void zzm(final String s) {
        zzb(new File(s));
    }
    
    public final Context getContext() {
        return this.zzrt;
    }
    
    public final boolean isInitialized() {
        return this.zzsh;
    }
    
    public final Method zza(final String s, final String s2) {
        final zzeg zzeg = this.zzsg.get(new Pair((Object)s, (Object)s2));
        if (zzeg == null) {
            return null;
        }
        return zzeg.zzaw();
    }
    
    @VisibleForTesting
    final void zza(final int n, final boolean b) {
        if (this.zzsf) {
            final Future<?> submit = this.zzru.submit(new zzdc(this, n, b));
            if (n == 0) {
                this.zzsc = submit;
            }
        }
    }
    
    public final boolean zza(final String s, final String s2, final Class<?>... array) {
        if (!this.zzsg.containsKey(new Pair((Object)s, (Object)s2))) {
            this.zzsg.put((Pair<String, String>)new Pair((Object)s, (Object)s2), new zzeg(this, s, s2, array));
            return true;
        }
        return false;
    }
    
    public final ExecutorService zzab() {
        return this.zzru;
    }
    
    public final DexClassLoader zzac() {
        return this.zzrv;
    }
    
    public final zzck zzad() {
        return this.zzrw;
    }
    
    public final byte[] zzae() {
        return this.zzrx;
    }
    
    public final boolean zzaf() {
        return this.zzse;
    }
    
    public final zzcc zzag() {
        return this.zzsd;
    }
    
    public final boolean zzah() {
        return this.zzsf;
    }
    
    public final boolean zzai() {
        return this.zzsi;
    }
    
    public final zzba zzaj() {
        return this.zzsb;
    }
    
    public final Future zzak() {
        return this.zzsc;
    }
    
    public final AdvertisingIdClient zzan() {
        if (!this.zzqt) {
            return null;
        }
        if (this.zzry != null) {
            return this.zzry;
        }
        Label_0049: {
            if (this.zzrz == null) {
                break Label_0049;
            }
            try {
                this.zzrz.get(2000L, TimeUnit.MILLISECONDS);
                this.zzrz = null;
                return this.zzry;
            }
            catch (TimeoutException ex) {
                this.zzrz.cancel(true);
                return this.zzry;
            }
            catch (ExecutionException ex2) {
                return this.zzry;
            }
            catch (InterruptedException ex3) {
                return this.zzry;
            }
        }
    }
    
    @VisibleForTesting
    final zzba zzb(final int n, final boolean b) {
        Label_0019: {
            if (n <= 0 || !b) {
                break Label_0019;
            }
            final long n2 = n * 1000;
            try {
                Thread.sleep(n2);
                return this.zzam();
            }
            catch (InterruptedException ex) {
                return this.zzam();
            }
        }
    }
    
    public final int zzx() {
        int zzx = Integer.MIN_VALUE;
        if (this.zzsd != null) {
            zzx = zzcc.zzx();
        }
        return zzx;
    }
    
    final class zza extends BroadcastReceiver
    {
        private zza() {
        }
        
        public final void onReceive(final Context context, final Intent intent) {
            if ("android.intent.action.USER_PRESENT".equals(intent.getAction())) {
                zzcz.this.zzsi = true;
            }
            else if ("android.intent.action.SCREEN_OFF".equals(intent.getAction())) {
                zzcz.this.zzsi = false;
            }
        }
    }
}
