// 
// Decompiled by Procyon v0.5.34
// 

package com.google.android.gms.internal.ads;

import java.lang.reflect.InvocationTargetException;
import java.util.concurrent.ExecutionException;

public final class zzdo extends zzei
{
    private static final Object zztn;
    private static volatile zzbj zzto;
    private zzax zztp;
    
    static {
        zzdo.zzto = null;
        zztn = new Object();
    }
    
    public zzdo(final zzcz zzcz, final String s, final String s2, final zzba zzba, final int n, final int n2, final zzax zztp) {
        super(zzcz, s, s2, zzba, n, 27);
        this.zztp = null;
        this.zztp = zztp;
    }
    
    private final String zzas() {
        try {
            if (this.zzps.zzak() != null) {
                this.zzps.zzak().get();
            }
            final zzba zzaj = this.zzps.zzaj();
            if (zzaj != null && zzaj.zzcx != null) {
                return zzaj.zzcx;
            }
            goto Label_0050;
        }
        catch (InterruptedException ex) {}
        catch (ExecutionException ex2) {
            goto Label_0050;
        }
    }
    
    @Override
    protected final void zzar() throws IllegalAccessException, InvocationTargetException {
        // 
        // This method could not be decompiled.
        // 
        // Original Bytecode:
        // 
        //     1: istore_3       
        //     2: getstatic       com/google/android/gms/internal/ads/zzdo.zzto:Lcom/google/android/gms/internal/ads/zzbj;
        //     5: ifnull          48
        //     8: getstatic       com/google/android/gms/internal/ads/zzdo.zzto:Lcom/google/android/gms/internal/ads/zzbj;
        //    11: getfield        com/google/android/gms/internal/ads/zzbj.zzcx:Ljava/lang/String;
        //    14: invokestatic    com/google/android/gms/internal/ads/zzdg.zzo:(Ljava/lang/String;)Z
        //    17: ifne            48
        //    20: getstatic       com/google/android/gms/internal/ads/zzdo.zzto:Lcom/google/android/gms/internal/ads/zzbj;
        //    23: getfield        com/google/android/gms/internal/ads/zzbj.zzcx:Ljava/lang/String;
        //    26: ldc             "E"
        //    28: invokevirtual   java/lang/String.equals:(Ljava/lang/Object;)Z
        //    31: ifne            48
        //    34: getstatic       com/google/android/gms/internal/ads/zzdo.zzto:Lcom/google/android/gms/internal/ads/zzbj;
        //    37: getfield        com/google/android/gms/internal/ads/zzbj.zzcx:Ljava/lang/String;
        //    40: ldc             "0000000000000000000000000000000000000000000000000000000000000000"
        //    42: invokevirtual   java/lang/String.equals:(Ljava/lang/Object;)Z
        //    45: ifeq            274
        //    48: iconst_1       
        //    49: istore_1       
        //    50: iload_1        
        //    51: ifeq            187
        //    54: getstatic       com/google/android/gms/internal/ads/zzdo.zztn:Ljava/lang/Object;
        //    57: astore          5
        //    59: aload           5
        //    61: monitorenter   
        //    62: aload_0        
        //    63: getfield        com/google/android/gms/internal/ads/zzdo.zztp:Lcom/google/android/gms/internal/ads/zzax;
        //    66: astore          6
        //    68: aconst_null    
        //    69: invokestatic    com/google/android/gms/internal/ads/zzdg.zzo:(Ljava/lang/String;)Z
        //    72: ifne            279
        //    75: iconst_4       
        //    76: istore_1       
        //    77: aload_0        
        //    78: getfield        com/google/android/gms/internal/ads/zzdo.zztz:Ljava/lang/reflect/Method;
        //    81: astore          8
        //    83: aload_0        
        //    84: getfield        com/google/android/gms/internal/ads/zzdo.zzps:Lcom/google/android/gms/internal/ads/zzcz;
        //    87: invokevirtual   com/google/android/gms/internal/ads/zzcz.getContext:()Landroid/content/Context;
        //    90: astore          7
        //    92: iload_1        
        //    93: iconst_2       
        //    94: if_icmpne       455
        //    97: iconst_1       
        //    98: istore          4
        //   100: getstatic       com/google/android/gms/internal/ads/zznk.zzbav:Lcom/google/android/gms/internal/ads/zzna;
        //   103: astore          6
        //   105: new             Lcom/google/android/gms/internal/ads/zzbj;
        //   108: dup            
        //   109: aload           8
        //   111: aconst_null    
        //   112: iconst_3       
        //   113: anewarray       Ljava/lang/Object;
        //   116: dup            
        //   117: iconst_0       
        //   118: aload           7
        //   120: aastore        
        //   121: dup            
        //   122: iconst_1       
        //   123: iload           4
        //   125: invokestatic    java/lang/Boolean.valueOf:(Z)Ljava/lang/Boolean;
        //   128: aastore        
        //   129: dup            
        //   130: iconst_2       
        //   131: invokestatic    com/google/android/gms/internal/ads/zzkb.zzik:()Lcom/google/android/gms/internal/ads/zzni;
        //   134: aload           6
        //   136: invokevirtual   com/google/android/gms/internal/ads/zzni.zzd:(Lcom/google/android/gms/internal/ads/zzna;)Ljava/lang/Object;
        //   139: aastore        
        //   140: invokevirtual   java/lang/reflect/Method.invoke:(Ljava/lang/Object;[Ljava/lang/Object;)Ljava/lang/Object;
        //   143: checkcast       Ljava/lang/String;
        //   146: invokespecial   com/google/android/gms/internal/ads/zzbj.<init>:(Ljava/lang/String;)V
        //   149: astore          6
        //   151: aload           6
        //   153: putstatic       com/google/android/gms/internal/ads/zzdo.zzto:Lcom/google/android/gms/internal/ads/zzbj;
        //   156: aload           6
        //   158: getfield        com/google/android/gms/internal/ads/zzbj.zzcx:Ljava/lang/String;
        //   161: invokestatic    com/google/android/gms/internal/ads/zzdg.zzo:(Ljava/lang/String;)Z
        //   164: ifne            413
        //   167: getstatic       com/google/android/gms/internal/ads/zzdo.zzto:Lcom/google/android/gms/internal/ads/zzbj;
        //   170: getfield        com/google/android/gms/internal/ads/zzbj.zzcx:Ljava/lang/String;
        //   173: ldc             "E"
        //   175: invokevirtual   java/lang/String.equals:(Ljava/lang/Object;)Z
        //   178: ifeq            184
        //   181: goto            413
        //   184: aload           5
        //   186: monitorexit    
        //   187: aload_0        
        //   188: getfield        com/google/android/gms/internal/ads/zzdo.zztq:Lcom/google/android/gms/internal/ads/zzba;
        //   191: astore          6
        //   193: aload           6
        //   195: monitorenter   
        //   196: getstatic       com/google/android/gms/internal/ads/zzdo.zzto:Lcom/google/android/gms/internal/ads/zzbj;
        //   199: ifnull          270
        //   202: aload_0        
        //   203: getfield        com/google/android/gms/internal/ads/zzdo.zztq:Lcom/google/android/gms/internal/ads/zzba;
        //   206: getstatic       com/google/android/gms/internal/ads/zzdo.zzto:Lcom/google/android/gms/internal/ads/zzbj;
        //   209: getfield        com/google/android/gms/internal/ads/zzbj.zzcx:Ljava/lang/String;
        //   212: putfield        com/google/android/gms/internal/ads/zzba.zzcx:Ljava/lang/String;
        //   215: aload_0        
        //   216: getfield        com/google/android/gms/internal/ads/zzdo.zztq:Lcom/google/android/gms/internal/ads/zzba;
        //   219: getstatic       com/google/android/gms/internal/ads/zzdo.zzto:Lcom/google/android/gms/internal/ads/zzbj;
        //   222: getfield        com/google/android/gms/internal/ads/zzbj.zzhx:J
        //   225: invokestatic    java/lang/Long.valueOf:(J)Ljava/lang/Long;
        //   228: putfield        com/google/android/gms/internal/ads/zzba.zzeb:Ljava/lang/Long;
        //   231: aload_0        
        //   232: getfield        com/google/android/gms/internal/ads/zzdo.zztq:Lcom/google/android/gms/internal/ads/zzba;
        //   235: getstatic       com/google/android/gms/internal/ads/zzdo.zzto:Lcom/google/android/gms/internal/ads/zzbj;
        //   238: getfield        com/google/android/gms/internal/ads/zzbj.zzcz:Ljava/lang/String;
        //   241: putfield        com/google/android/gms/internal/ads/zzba.zzcz:Ljava/lang/String;
        //   244: aload_0        
        //   245: getfield        com/google/android/gms/internal/ads/zzdo.zztq:Lcom/google/android/gms/internal/ads/zzba;
        //   248: getstatic       com/google/android/gms/internal/ads/zzdo.zzto:Lcom/google/android/gms/internal/ads/zzbj;
        //   251: getfield        com/google/android/gms/internal/ads/zzbj.zzda:Ljava/lang/String;
        //   254: putfield        com/google/android/gms/internal/ads/zzba.zzda:Ljava/lang/String;
        //   257: aload_0        
        //   258: getfield        com/google/android/gms/internal/ads/zzdo.zztq:Lcom/google/android/gms/internal/ads/zzba;
        //   261: getstatic       com/google/android/gms/internal/ads/zzdo.zzto:Lcom/google/android/gms/internal/ads/zzbj;
        //   264: getfield        com/google/android/gms/internal/ads/zzbj.zzdb:Ljava/lang/String;
        //   267: putfield        com/google/android/gms/internal/ads/zzba.zzdb:Ljava/lang/String;
        //   270: aload           6
        //   272: monitorexit    
        //   273: return         
        //   274: iconst_0       
        //   275: istore_1       
        //   276: goto            50
        //   279: aload_0        
        //   280: getfield        com/google/android/gms/internal/ads/zzdo.zztp:Lcom/google/android/gms/internal/ads/zzax;
        //   283: astore          6
        //   285: aconst_null    
        //   286: invokestatic    com/google/android/gms/internal/ads/zzdg.zzo:(Ljava/lang/String;)Z
        //   289: pop            
        //   290: iconst_0       
        //   291: invokestatic    java/lang/Boolean.valueOf:(Z)Ljava/lang/Boolean;
        //   294: invokevirtual   java/lang/Boolean.booleanValue:()Z
        //   297: ifeq            445
        //   300: aload_0        
        //   301: getfield        com/google/android/gms/internal/ads/zzdo.zzps:Lcom/google/android/gms/internal/ads/zzcz;
        //   304: invokevirtual   com/google/android/gms/internal/ads/zzcz.zzah:()Z
        //   307: ifeq            450
        //   310: getstatic       com/google/android/gms/internal/ads/zznk.zzbbb:Lcom/google/android/gms/internal/ads/zzna;
        //   313: astore          6
        //   315: invokestatic    com/google/android/gms/internal/ads/zzkb.zzik:()Lcom/google/android/gms/internal/ads/zzni;
        //   318: aload           6
        //   320: invokevirtual   com/google/android/gms/internal/ads/zzni.zzd:(Lcom/google/android/gms/internal/ads/zzna;)Ljava/lang/Object;
        //   323: checkcast       Ljava/lang/Boolean;
        //   326: invokevirtual   java/lang/Boolean.booleanValue:()Z
        //   329: ifeq            450
        //   332: getstatic       com/google/android/gms/internal/ads/zznk.zzbbc:Lcom/google/android/gms/internal/ads/zzna;
        //   335: astore          6
        //   337: invokestatic    com/google/android/gms/internal/ads/zzkb.zzik:()Lcom/google/android/gms/internal/ads/zzni;
        //   340: aload           6
        //   342: invokevirtual   com/google/android/gms/internal/ads/zzni.zzd:(Lcom/google/android/gms/internal/ads/zzna;)Ljava/lang/Object;
        //   345: checkcast       Ljava/lang/Boolean;
        //   348: invokevirtual   java/lang/Boolean.booleanValue:()Z
        //   351: ifeq            450
        //   354: iconst_1       
        //   355: istore_2       
        //   356: goto            439
        //   359: getstatic       com/google/android/gms/internal/ads/zzdo.zzto:Lcom/google/android/gms/internal/ads/zzbj;
        //   362: astore          6
        //   364: new             Ljava/lang/NullPointerException;
        //   367: dup            
        //   368: invokespecial   java/lang/NullPointerException.<init>:()V
        //   371: athrow         
        //   372: astore          6
        //   374: aload           5
        //   376: monitorexit    
        //   377: aload           6
        //   379: athrow         
        //   380: aload_0        
        //   381: invokespecial   com/google/android/gms/internal/ads/zzdo.zzas:()Ljava/lang/String;
        //   384: astore          6
        //   386: aload           6
        //   388: invokestatic    com/google/android/gms/internal/ads/zzdg.zzo:(Ljava/lang/String;)Z
        //   391: ifne            184
        //   394: getstatic       com/google/android/gms/internal/ads/zzdo.zzto:Lcom/google/android/gms/internal/ads/zzbj;
        //   397: aload           6
        //   399: putfield        com/google/android/gms/internal/ads/zzbj.zzcx:Ljava/lang/String;
        //   402: goto            184
        //   405: astore          5
        //   407: aload           6
        //   409: monitorexit    
        //   410: aload           5
        //   412: athrow         
        //   413: iload_1        
        //   414: tableswitch {
        //                6: 380
        //                7: 359
        //          default: 436
        //        }
        //   436: goto            184
        //   439: iload_3        
        //   440: istore_1       
        //   441: iload_2        
        //   442: ifne            77
        //   445: iconst_2       
        //   446: istore_1       
        //   447: goto            77
        //   450: iconst_0       
        //   451: istore_2       
        //   452: goto            439
        //   455: iconst_0       
        //   456: istore          4
        //   458: goto            100
        //    Exceptions:
        //  throws java.lang.IllegalAccessException
        //  throws java.lang.reflect.InvocationTargetException
        //    Exceptions:
        //  Try           Handler
        //  Start  End    Start  End    Type
        //  -----  -----  -----  -----  ----
        //  62     75     372    380    Any
        //  77     92     372    380    Any
        //  100    181    372    380    Any
        //  184    187    372    380    Any
        //  196    270    405    413    Any
        //  270    273    405    413    Any
        //  279    354    372    380    Any
        //  359    372    372    380    Any
        //  374    377    372    380    Any
        //  380    402    372    380    Any
        //  407    410    405    413    Any
        // 
        // The error that occurred was:
        // 
        // java.lang.IllegalStateException: Expression is linked from several locations: Label_0270:
        //     at com.strobel.decompiler.ast.Error.expressionLinkedFromMultipleLocations(Error.java:27)
        //     at com.strobel.decompiler.ast.AstOptimizer.mergeDisparateObjectInitializations(AstOptimizer.java:2596)
        //     at com.strobel.decompiler.ast.AstOptimizer.optimize(AstOptimizer.java:235)
        //     at com.strobel.decompiler.ast.AstOptimizer.optimize(AstOptimizer.java:42)
        //     at com.strobel.decompiler.languages.java.ast.AstMethodBodyBuilder.createMethodBody(AstMethodBodyBuilder.java:214)
        //     at com.strobel.decompiler.languages.java.ast.AstMethodBodyBuilder.createMethodBody(AstMethodBodyBuilder.java:99)
        //     at com.strobel.decompiler.languages.java.ast.AstBuilder.createMethodBody(AstBuilder.java:782)
        //     at com.strobel.decompiler.languages.java.ast.AstBuilder.createMethod(AstBuilder.java:675)
        //     at com.strobel.decompiler.languages.java.ast.AstBuilder.addTypeMembers(AstBuilder.java:552)
        //     at com.strobel.decompiler.languages.java.ast.AstBuilder.createTypeCore(AstBuilder.java:519)
        //     at com.strobel.decompiler.languages.java.ast.AstBuilder.createTypeNoCache(AstBuilder.java:161)
        //     at com.strobel.decompiler.languages.java.ast.AstBuilder.createType(AstBuilder.java:150)
        //     at com.strobel.decompiler.languages.java.ast.AstBuilder.addType(AstBuilder.java:125)
        //     at com.strobel.decompiler.languages.java.JavaLanguage.buildAst(JavaLanguage.java:71)
        //     at com.strobel.decompiler.languages.java.JavaLanguage.decompileType(JavaLanguage.java:59)
        //     at com.strobel.decompiler.DecompilerDriver.decompileType(DecompilerDriver.java:330)
        //     at com.strobel.decompiler.DecompilerDriver.decompileJar(DecompilerDriver.java:251)
        //     at com.strobel.decompiler.DecompilerDriver.main(DecompilerDriver.java:126)
        // 
        throw new IllegalStateException("An error occurred while decompiling this method.");
    }
}
