// 
// Decompiled by Procyon v0.5.34
// 

package com.google.android.gms.internal.ads;

import java.util.ArrayList;
import java.util.List;
import android.content.Context;

@zzadh
public final class zzxk implements zzww
{
    private final Context mContext;
    private final Object mLock;
    private final long mStartTime;
    private final boolean zzael;
    private final zzwy zzbtj;
    private final boolean zzbtn;
    private final boolean zzbto;
    private final zzaef zzbuc;
    private final long zzbud;
    private boolean zzbuf;
    private final String zzbuh;
    private List<zzxe> zzbui;
    private zzxb zzbum;
    private final zznx zzvr;
    private final zzxn zzwh;
    
    public zzxk(final Context mContext, final zzaef zzbuc, final zzxn zzwh, final zzwy zzbtj, final boolean zzael, final boolean zzbtn, final String zzbuh, final long mStartTime, final long zzbud, final zznx zzvr, final boolean zzbto) {
        this.mLock = new Object();
        this.zzbuf = false;
        this.zzbui = new ArrayList<zzxe>();
        this.mContext = mContext;
        this.zzbuc = zzbuc;
        this.zzwh = zzwh;
        this.zzbtj = zzbtj;
        this.zzael = zzael;
        this.zzbtn = zzbtn;
        this.zzbuh = zzbuh;
        this.mStartTime = mStartTime;
        this.zzbud = zzbud;
        this.zzvr = zzvr;
        this.zzbto = zzbto;
    }
    
    @Override
    public final void cancel() {
        synchronized (this.mLock) {
            this.zzbuf = true;
            if (this.zzbum != null) {
                this.zzbum.cancel();
            }
        }
    }
    
    @Override
    public final zzxe zzh(final List<zzwx> p0) {
        // 
        // This method could not be decompiled.
        // 
        // Original Bytecode:
        // 
        //     2: invokestatic    com/google/android/gms/internal/ads/zzakb.zzck:(Ljava/lang/String;)V
        //     5: new             Ljava/util/ArrayList;
        //     8: dup            
        //     9: invokespecial   java/util/ArrayList.<init>:()V
        //    12: astore          8
        //    14: aload_0        
        //    15: getfield        com/google/android/gms/internal/ads/zzxk.zzvr:Lcom/google/android/gms/internal/ads/zznx;
        //    18: invokevirtual   com/google/android/gms/internal/ads/zznx.zzjj:()Lcom/google/android/gms/internal/ads/zznv;
        //    21: astore          9
        //    23: aload_0        
        //    24: getfield        com/google/android/gms/internal/ads/zzxk.zzbuc:Lcom/google/android/gms/internal/ads/zzaef;
        //    27: getfield        com/google/android/gms/internal/ads/zzaef.zzacv:Lcom/google/android/gms/internal/ads/zzjn;
        //    30: astore          6
        //    32: iconst_2       
        //    33: newarray        I
        //    35: astore          7
        //    37: aload           6
        //    39: getfield        com/google/android/gms/internal/ads/zzjn.zzard:[Lcom/google/android/gms/internal/ads/zzjn;
        //    42: ifnull          568
        //    45: invokestatic    com/google/android/gms/ads/internal/zzbv.zzfd:()Lcom/google/android/gms/internal/ads/zzxg;
        //    48: pop            
        //    49: aload_0        
        //    50: getfield        com/google/android/gms/internal/ads/zzxk.zzbuh:Ljava/lang/String;
        //    53: aload           7
        //    55: invokestatic    com/google/android/gms/internal/ads/zzxg.zza:(Ljava/lang/String;[I)Z
        //    58: ifeq            568
        //    61: aload           7
        //    63: iconst_0       
        //    64: iaload         
        //    65: istore_3       
        //    66: aload           7
        //    68: iconst_1       
        //    69: iaload         
        //    70: istore          4
        //    72: aload           6
        //    74: getfield        com/google/android/gms/internal/ads/zzjn.zzard:[Lcom/google/android/gms/internal/ads/zzjn;
        //    77: astore          10
        //    79: aload           10
        //    81: arraylength    
        //    82: istore          5
        //    84: iconst_0       
        //    85: istore_2       
        //    86: iload_2        
        //    87: iload           5
        //    89: if_icmpge       568
        //    92: aload           10
        //    94: iload_2        
        //    95: aaload         
        //    96: astore          7
        //    98: iload_3        
        //    99: aload           7
        //   101: getfield        com/google/android/gms/internal/ads/zzjn.width:I
        //   104: if_icmpne       250
        //   107: iload           4
        //   109: aload           7
        //   111: getfield        com/google/android/gms/internal/ads/zzjn.height:I
        //   114: if_icmpne       250
        //   117: aload           7
        //   119: astore          6
        //   121: aload_1        
        //   122: invokeinterface java/util/List.iterator:()Ljava/util/Iterator;
        //   127: astore          7
        //   129: aload           7
        //   131: invokeinterface java/util/Iterator.hasNext:()Z
        //   136: ifeq            533
        //   139: aload           7
        //   141: invokeinterface java/util/Iterator.next:()Ljava/lang/Object;
        //   146: checkcast       Lcom/google/android/gms/internal/ads/zzwx;
        //   149: astore          10
        //   151: aload           10
        //   153: getfield        com/google/android/gms/internal/ads/zzwx.zzbrs:Ljava/lang/String;
        //   156: invokestatic    java/lang/String.valueOf:(Ljava/lang/Object;)Ljava/lang/String;
        //   159: astore_1       
        //   160: aload_1        
        //   161: invokevirtual   java/lang/String.length:()I
        //   164: ifeq            257
        //   167: ldc             "Trying mediation network: "
        //   169: aload_1        
        //   170: invokevirtual   java/lang/String.concat:(Ljava/lang/String;)Ljava/lang/String;
        //   173: astore_1       
        //   174: aload_1        
        //   175: invokestatic    com/google/android/gms/internal/ads/zzakb.zzdj:(Ljava/lang/String;)V
        //   178: aload           10
        //   180: getfield        com/google/android/gms/internal/ads/zzwx.zzbrt:Ljava/util/List;
        //   183: invokeinterface java/util/List.iterator:()Ljava/util/Iterator;
        //   188: astore          11
        //   190: aload           11
        //   192: invokeinterface java/util/Iterator.hasNext:()Z
        //   197: ifeq            129
        //   200: aload           11
        //   202: invokeinterface java/util/Iterator.next:()Ljava/lang/Object;
        //   207: checkcast       Ljava/lang/String;
        //   210: astore          12
        //   212: aload_0        
        //   213: getfield        com/google/android/gms/internal/ads/zzxk.zzvr:Lcom/google/android/gms/internal/ads/zznx;
        //   216: invokevirtual   com/google/android/gms/internal/ads/zznx.zzjj:()Lcom/google/android/gms/internal/ads/zznv;
        //   219: astore          13
        //   221: aload_0        
        //   222: getfield        com/google/android/gms/internal/ads/zzxk.mLock:Ljava/lang/Object;
        //   225: astore_1       
        //   226: aload_1        
        //   227: monitorenter   
        //   228: aload_0        
        //   229: getfield        com/google/android/gms/internal/ads/zzxk.zzbuf:Z
        //   232: ifeq            270
        //   235: new             Lcom/google/android/gms/internal/ads/zzxe;
        //   238: dup            
        //   239: iconst_m1      
        //   240: invokespecial   com/google/android/gms/internal/ads/zzxe.<init>:(I)V
        //   243: astore          6
        //   245: aload_1        
        //   246: monitorexit    
        //   247: aload           6
        //   249: areturn        
        //   250: iload_2        
        //   251: iconst_1       
        //   252: iadd           
        //   253: istore_2       
        //   254: goto            86
        //   257: new             Ljava/lang/String;
        //   260: dup            
        //   261: ldc             "Trying mediation network: "
        //   263: invokespecial   java/lang/String.<init>:(Ljava/lang/String;)V
        //   266: astore_1       
        //   267: goto            174
        //   270: aload_0        
        //   271: new             Lcom/google/android/gms/internal/ads/zzxb;
        //   274: dup            
        //   275: aload_0        
        //   276: getfield        com/google/android/gms/internal/ads/zzxk.mContext:Landroid/content/Context;
        //   279: aload           12
        //   281: aload_0        
        //   282: getfield        com/google/android/gms/internal/ads/zzxk.zzwh:Lcom/google/android/gms/internal/ads/zzxn;
        //   285: aload_0        
        //   286: getfield        com/google/android/gms/internal/ads/zzxk.zzbtj:Lcom/google/android/gms/internal/ads/zzwy;
        //   289: aload           10
        //   291: aload_0        
        //   292: getfield        com/google/android/gms/internal/ads/zzxk.zzbuc:Lcom/google/android/gms/internal/ads/zzaef;
        //   295: getfield        com/google/android/gms/internal/ads/zzaef.zzccv:Lcom/google/android/gms/internal/ads/zzjj;
        //   298: aload           6
        //   300: aload_0        
        //   301: getfield        com/google/android/gms/internal/ads/zzxk.zzbuc:Lcom/google/android/gms/internal/ads/zzaef;
        //   304: getfield        com/google/android/gms/internal/ads/zzaef.zzacr:Lcom/google/android/gms/internal/ads/zzang;
        //   307: aload_0        
        //   308: getfield        com/google/android/gms/internal/ads/zzxk.zzael:Z
        //   311: aload_0        
        //   312: getfield        com/google/android/gms/internal/ads/zzxk.zzbtn:Z
        //   315: aload_0        
        //   316: getfield        com/google/android/gms/internal/ads/zzxk.zzbuc:Lcom/google/android/gms/internal/ads/zzaef;
        //   319: getfield        com/google/android/gms/internal/ads/zzaef.zzadj:Lcom/google/android/gms/internal/ads/zzpl;
        //   322: aload_0        
        //   323: getfield        com/google/android/gms/internal/ads/zzxk.zzbuc:Lcom/google/android/gms/internal/ads/zzaef;
        //   326: getfield        com/google/android/gms/internal/ads/zzaef.zzads:Ljava/util/List;
        //   329: aload_0        
        //   330: getfield        com/google/android/gms/internal/ads/zzxk.zzbuc:Lcom/google/android/gms/internal/ads/zzaef;
        //   333: getfield        com/google/android/gms/internal/ads/zzaef.zzcdk:Ljava/util/List;
        //   336: aload_0        
        //   337: getfield        com/google/android/gms/internal/ads/zzxk.zzbuc:Lcom/google/android/gms/internal/ads/zzaef;
        //   340: getfield        com/google/android/gms/internal/ads/zzaef.zzcef:Ljava/util/List;
        //   343: aload_0        
        //   344: getfield        com/google/android/gms/internal/ads/zzxk.zzbto:Z
        //   347: invokespecial   com/google/android/gms/internal/ads/zzxb.<init>:(Landroid/content/Context;Ljava/lang/String;Lcom/google/android/gms/internal/ads/zzxn;Lcom/google/android/gms/internal/ads/zzwy;Lcom/google/android/gms/internal/ads/zzwx;Lcom/google/android/gms/internal/ads/zzjj;Lcom/google/android/gms/internal/ads/zzjn;Lcom/google/android/gms/internal/ads/zzang;ZZLcom/google/android/gms/internal/ads/zzpl;Ljava/util/List;Ljava/util/List;Ljava/util/List;Z)V
        //   350: putfield        com/google/android/gms/internal/ads/zzxk.zzbum:Lcom/google/android/gms/internal/ads/zzxb;
        //   353: aload_1        
        //   354: monitorexit    
        //   355: aload_0        
        //   356: getfield        com/google/android/gms/internal/ads/zzxk.zzbum:Lcom/google/android/gms/internal/ads/zzxb;
        //   359: aload_0        
        //   360: getfield        com/google/android/gms/internal/ads/zzxk.mStartTime:J
        //   363: aload_0        
        //   364: getfield        com/google/android/gms/internal/ads/zzxk.zzbud:J
        //   367: invokevirtual   com/google/android/gms/internal/ads/zzxb.zza:(JJ)Lcom/google/android/gms/internal/ads/zzxe;
        //   370: astore_1       
        //   371: aload_0        
        //   372: getfield        com/google/android/gms/internal/ads/zzxk.zzbui:Ljava/util/List;
        //   375: aload_1        
        //   376: invokeinterface java/util/List.add:(Ljava/lang/Object;)Z
        //   381: pop            
        //   382: aload_1        
        //   383: getfield        com/google/android/gms/internal/ads/zzxe.zzbtv:I
        //   386: ifne            478
        //   389: ldc             "Adapter succeeded."
        //   391: invokestatic    com/google/android/gms/internal/ads/zzakb.zzck:(Ljava/lang/String;)V
        //   394: aload_0        
        //   395: getfield        com/google/android/gms/internal/ads/zzxk.zzvr:Lcom/google/android/gms/internal/ads/zznx;
        //   398: ldc             "mediation_network_succeed"
        //   400: aload           12
        //   402: invokevirtual   com/google/android/gms/internal/ads/zznx.zze:(Ljava/lang/String;Ljava/lang/String;)V
        //   405: aload           8
        //   407: invokeinterface java/util/List.isEmpty:()Z
        //   412: ifne            431
        //   415: aload_0        
        //   416: getfield        com/google/android/gms/internal/ads/zzxk.zzvr:Lcom/google/android/gms/internal/ads/zznx;
        //   419: ldc             "mediation_networks_fail"
        //   421: ldc             ","
        //   423: aload           8
        //   425: invokestatic    android/text/TextUtils.join:(Ljava/lang/CharSequence;Ljava/lang/Iterable;)Ljava/lang/String;
        //   428: invokevirtual   com/google/android/gms/internal/ads/zznx.zze:(Ljava/lang/String;Ljava/lang/String;)V
        //   431: aload_0        
        //   432: getfield        com/google/android/gms/internal/ads/zzxk.zzvr:Lcom/google/android/gms/internal/ads/zznx;
        //   435: aload           13
        //   437: iconst_1       
        //   438: anewarray       Ljava/lang/String;
        //   441: dup            
        //   442: iconst_0       
        //   443: ldc             "mls"
        //   445: aastore        
        //   446: invokevirtual   com/google/android/gms/internal/ads/zznx.zza:(Lcom/google/android/gms/internal/ads/zznv;[Ljava/lang/String;)Z
        //   449: pop            
        //   450: aload_0        
        //   451: getfield        com/google/android/gms/internal/ads/zzxk.zzvr:Lcom/google/android/gms/internal/ads/zznx;
        //   454: aload           9
        //   456: iconst_1       
        //   457: anewarray       Ljava/lang/String;
        //   460: dup            
        //   461: iconst_0       
        //   462: ldc             "ttm"
        //   464: aastore        
        //   465: invokevirtual   com/google/android/gms/internal/ads/zznx.zza:(Lcom/google/android/gms/internal/ads/zznv;[Ljava/lang/String;)Z
        //   468: pop            
        //   469: aload_1        
        //   470: areturn        
        //   471: astore          6
        //   473: aload_1        
        //   474: monitorexit    
        //   475: aload           6
        //   477: athrow         
        //   478: aload           8
        //   480: aload           12
        //   482: invokeinterface java/util/List.add:(Ljava/lang/Object;)Z
        //   487: pop            
        //   488: aload_0        
        //   489: getfield        com/google/android/gms/internal/ads/zzxk.zzvr:Lcom/google/android/gms/internal/ads/zznx;
        //   492: aload           13
        //   494: iconst_1       
        //   495: anewarray       Ljava/lang/String;
        //   498: dup            
        //   499: iconst_0       
        //   500: ldc             "mlf"
        //   502: aastore        
        //   503: invokevirtual   com/google/android/gms/internal/ads/zznx.zza:(Lcom/google/android/gms/internal/ads/zznv;[Ljava/lang/String;)Z
        //   506: pop            
        //   507: aload_1        
        //   508: getfield        com/google/android/gms/internal/ads/zzxe.zzbtx:Lcom/google/android/gms/internal/ads/zzxq;
        //   511: ifnull          190
        //   514: getstatic       com/google/android/gms/internal/ads/zzakk.zzcrm:Landroid/os/Handler;
        //   517: new             Lcom/google/android/gms/internal/ads/zzxl;
        //   520: dup            
        //   521: aload_0        
        //   522: aload_1        
        //   523: invokespecial   com/google/android/gms/internal/ads/zzxl.<init>:(Lcom/google/android/gms/internal/ads/zzxk;Lcom/google/android/gms/internal/ads/zzxe;)V
        //   526: invokevirtual   android/os/Handler.post:(Ljava/lang/Runnable;)Z
        //   529: pop            
        //   530: goto            190
        //   533: aload           8
        //   535: invokeinterface java/util/List.isEmpty:()Z
        //   540: ifne            559
        //   543: aload_0        
        //   544: getfield        com/google/android/gms/internal/ads/zzxk.zzvr:Lcom/google/android/gms/internal/ads/zznx;
        //   547: ldc             "mediation_networks_fail"
        //   549: ldc             ","
        //   551: aload           8
        //   553: invokestatic    android/text/TextUtils.join:(Ljava/lang/CharSequence;Ljava/lang/Iterable;)Ljava/lang/String;
        //   556: invokevirtual   com/google/android/gms/internal/ads/zznx.zze:(Ljava/lang/String;Ljava/lang/String;)V
        //   559: new             Lcom/google/android/gms/internal/ads/zzxe;
        //   562: dup            
        //   563: iconst_1       
        //   564: invokespecial   com/google/android/gms/internal/ads/zzxe.<init>:(I)V
        //   567: areturn        
        //   568: goto            121
        //    Signature:
        //  (Ljava/util/List<Lcom/google/android/gms/internal/ads/zzwx;>;)Lcom/google/android/gms/internal/ads/zzxe;
        //    Exceptions:
        //  Try           Handler
        //  Start  End    Start  End    Type
        //  -----  -----  -----  -----  ----
        //  228    247    471    478    Any
        //  270    355    471    478    Any
        //  473    475    471    478    Any
        // 
        // The error that occurred was:
        // 
        // java.lang.NullPointerException
        //     at com.strobel.assembler.ir.StackMappingVisitor.push(StackMappingVisitor.java:290)
        //     at com.strobel.assembler.ir.StackMappingVisitor$InstructionAnalyzer.execute(StackMappingVisitor.java:833)
        //     at com.strobel.assembler.ir.StackMappingVisitor$InstructionAnalyzer.visit(StackMappingVisitor.java:398)
        //     at com.strobel.decompiler.ast.AstBuilder.performStackAnalysis(AstBuilder.java:2030)
        //     at com.strobel.decompiler.ast.AstBuilder.build(AstBuilder.java:108)
        //     at com.strobel.decompiler.languages.java.ast.AstMethodBodyBuilder.createMethodBody(AstMethodBodyBuilder.java:211)
        //     at com.strobel.decompiler.languages.java.ast.AstMethodBodyBuilder.createMethodBody(AstMethodBodyBuilder.java:99)
        //     at com.strobel.decompiler.languages.java.ast.AstBuilder.createMethodBody(AstBuilder.java:782)
        //     at com.strobel.decompiler.languages.java.ast.AstBuilder.createMethod(AstBuilder.java:675)
        //     at com.strobel.decompiler.languages.java.ast.AstBuilder.addTypeMembers(AstBuilder.java:552)
        //     at com.strobel.decompiler.languages.java.ast.AstBuilder.createTypeCore(AstBuilder.java:519)
        //     at com.strobel.decompiler.languages.java.ast.AstBuilder.createTypeNoCache(AstBuilder.java:161)
        //     at com.strobel.decompiler.languages.java.ast.AstBuilder.createType(AstBuilder.java:150)
        //     at com.strobel.decompiler.languages.java.ast.AstBuilder.addType(AstBuilder.java:125)
        //     at com.strobel.decompiler.languages.java.JavaLanguage.buildAst(JavaLanguage.java:71)
        //     at com.strobel.decompiler.languages.java.JavaLanguage.decompileType(JavaLanguage.java:59)
        //     at com.strobel.decompiler.DecompilerDriver.decompileType(DecompilerDriver.java:330)
        //     at com.strobel.decompiler.DecompilerDriver.decompileJar(DecompilerDriver.java:251)
        //     at com.strobel.decompiler.DecompilerDriver.main(DecompilerDriver.java:126)
        // 
        throw new IllegalStateException("An error occurred while decompiling this method.");
    }
    
    @Override
    public final List<zzxe> zzme() {
        return this.zzbui;
    }
}
