// 
// Decompiled by Procyon v0.5.34
// 

package com.google.android.gms.internal.ads;

import android.support.annotation.WorkerThread;
import android.support.annotation.Nullable;

@zzadh
public final class zzanf implements zzamx
{
    @Nullable
    private final String zzcpq;
    
    public zzanf() {
        this(null);
    }
    
    public zzanf(@Nullable final String zzcpq) {
        this.zzcpq = zzcpq;
    }
    
    @WorkerThread
    @Override
    public final void zzcz(final String p0) {
        // 
        // This method could not be decompiled.
        // 
        // Original Bytecode:
        // 
        //     1: invokestatic    java/lang/String.valueOf:(Ljava/lang/Object;)Ljava/lang/String;
        //     4: astore_3       
        //     5: aload_3        
        //     6: invokevirtual   java/lang/String.length:()I
        //     9: ifeq            139
        //    12: ldc             "Pinging URL: "
        //    14: aload_3        
        //    15: invokevirtual   java/lang/String.concat:(Ljava/lang/String;)Ljava/lang/String;
        //    18: astore_3       
        //    19: aload_3        
        //    20: invokestatic    com/google/android/gms/internal/ads/zzane.zzck:(Ljava/lang/String;)V
        //    23: new             Ljava/net/URL;
        //    26: dup            
        //    27: aload_1        
        //    28: invokespecial   java/net/URL.<init>:(Ljava/lang/String;)V
        //    31: invokevirtual   java/net/URL.openConnection:()Ljava/net/URLConnection;
        //    34: checkcast       Ljava/net/HttpURLConnection;
        //    37: astore_3       
        //    38: invokestatic    com/google/android/gms/internal/ads/zzkb.zzif:()Lcom/google/android/gms/internal/ads/zzamu;
        //    41: pop            
        //    42: iconst_1       
        //    43: aload_3        
        //    44: aload_0        
        //    45: getfield        com/google/android/gms/internal/ads/zzanf.zzcpq:Ljava/lang/String;
        //    48: invokestatic    com/google/android/gms/internal/ads/zzamu.zza:(ZLjava/net/HttpURLConnection;Ljava/lang/String;)V
        //    51: new             Lcom/google/android/gms/internal/ads/zzamy;
        //    54: dup            
        //    55: invokespecial   com/google/android/gms/internal/ads/zzamy.<init>:()V
        //    58: astore          4
        //    60: aload           4
        //    62: aload_3        
        //    63: aconst_null    
        //    64: invokevirtual   com/google/android/gms/internal/ads/zzamy.zza:(Ljava/net/HttpURLConnection;[B)V
        //    67: aload_3        
        //    68: invokevirtual   java/net/HttpURLConnection.getResponseCode:()I
        //    71: istore_2       
        //    72: aload           4
        //    74: aload_3        
        //    75: iload_2        
        //    76: invokevirtual   com/google/android/gms/internal/ads/zzamy.zza:(Ljava/net/HttpURLConnection;I)V
        //    79: iload_2        
        //    80: sipush          200
        //    83: if_icmplt       93
        //    86: iload_2        
        //    87: sipush          300
        //    90: if_icmplt       134
        //    93: new             Ljava/lang/StringBuilder;
        //    96: dup            
        //    97: aload_1        
        //    98: invokestatic    java/lang/String.valueOf:(Ljava/lang/Object;)Ljava/lang/String;
        //   101: invokevirtual   java/lang/String.length:()I
        //   104: bipush          65
        //   106: iadd           
        //   107: invokespecial   java/lang/StringBuilder.<init>:(I)V
        //   110: ldc             "Received non-success response code "
        //   112: invokevirtual   java/lang/StringBuilder.append:(Ljava/lang/String;)Ljava/lang/StringBuilder;
        //   115: iload_2        
        //   116: invokevirtual   java/lang/StringBuilder.append:(I)Ljava/lang/StringBuilder;
        //   119: ldc             " from pinging URL: "
        //   121: invokevirtual   java/lang/StringBuilder.append:(Ljava/lang/String;)Ljava/lang/StringBuilder;
        //   124: aload_1        
        //   125: invokevirtual   java/lang/StringBuilder.append:(Ljava/lang/String;)Ljava/lang/StringBuilder;
        //   128: invokevirtual   java/lang/StringBuilder.toString:()Ljava/lang/String;
        //   131: invokestatic    com/google/android/gms/internal/ads/zzane.zzdk:(Ljava/lang/String;)V
        //   134: aload_3        
        //   135: invokevirtual   java/net/HttpURLConnection.disconnect:()V
        //   138: return         
        //   139: new             Ljava/lang/String;
        //   142: dup            
        //   143: ldc             "Pinging URL: "
        //   145: invokespecial   java/lang/String.<init>:(Ljava/lang/String;)V
        //   148: astore_3       
        //   149: goto            19
        //   152: astore_3       
        //   153: aload_3        
        //   154: invokevirtual   java/lang/IndexOutOfBoundsException.getMessage:()Ljava/lang/String;
        //   157: astore_3       
        //   158: new             Ljava/lang/StringBuilder;
        //   161: dup            
        //   162: aload_1        
        //   163: invokestatic    java/lang/String.valueOf:(Ljava/lang/Object;)Ljava/lang/String;
        //   166: invokevirtual   java/lang/String.length:()I
        //   169: bipush          32
        //   171: iadd           
        //   172: aload_3        
        //   173: invokestatic    java/lang/String.valueOf:(Ljava/lang/Object;)Ljava/lang/String;
        //   176: invokevirtual   java/lang/String.length:()I
        //   179: iadd           
        //   180: invokespecial   java/lang/StringBuilder.<init>:(I)V
        //   183: ldc             "Error while parsing ping URL: "
        //   185: invokevirtual   java/lang/StringBuilder.append:(Ljava/lang/String;)Ljava/lang/StringBuilder;
        //   188: aload_1        
        //   189: invokevirtual   java/lang/StringBuilder.append:(Ljava/lang/String;)Ljava/lang/StringBuilder;
        //   192: ldc             ". "
        //   194: invokevirtual   java/lang/StringBuilder.append:(Ljava/lang/String;)Ljava/lang/StringBuilder;
        //   197: aload_3        
        //   198: invokevirtual   java/lang/StringBuilder.append:(Ljava/lang/String;)Ljava/lang/StringBuilder;
        //   201: invokevirtual   java/lang/StringBuilder.toString:()Ljava/lang/String;
        //   204: invokestatic    com/google/android/gms/internal/ads/zzane.zzdk:(Ljava/lang/String;)V
        //   207: return         
        //   208: astore          4
        //   210: aload_3        
        //   211: invokevirtual   java/net/HttpURLConnection.disconnect:()V
        //   214: aload           4
        //   216: athrow         
        //   217: astore_3       
        //   218: aload_3        
        //   219: invokevirtual   java/io/IOException.getMessage:()Ljava/lang/String;
        //   222: astore_3       
        //   223: new             Ljava/lang/StringBuilder;
        //   226: dup            
        //   227: aload_1        
        //   228: invokestatic    java/lang/String.valueOf:(Ljava/lang/Object;)Ljava/lang/String;
        //   231: invokevirtual   java/lang/String.length:()I
        //   234: bipush          27
        //   236: iadd           
        //   237: aload_3        
        //   238: invokestatic    java/lang/String.valueOf:(Ljava/lang/Object;)Ljava/lang/String;
        //   241: invokevirtual   java/lang/String.length:()I
        //   244: iadd           
        //   245: invokespecial   java/lang/StringBuilder.<init>:(I)V
        //   248: ldc             "Error while pinging URL: "
        //   250: invokevirtual   java/lang/StringBuilder.append:(Ljava/lang/String;)Ljava/lang/StringBuilder;
        //   253: aload_1        
        //   254: invokevirtual   java/lang/StringBuilder.append:(Ljava/lang/String;)Ljava/lang/StringBuilder;
        //   257: ldc             ". "
        //   259: invokevirtual   java/lang/StringBuilder.append:(Ljava/lang/String;)Ljava/lang/StringBuilder;
        //   262: aload_3        
        //   263: invokevirtual   java/lang/StringBuilder.append:(Ljava/lang/String;)Ljava/lang/StringBuilder;
        //   266: invokevirtual   java/lang/StringBuilder.toString:()Ljava/lang/String;
        //   269: invokestatic    com/google/android/gms/internal/ads/zzane.zzdk:(Ljava/lang/String;)V
        //   272: return         
        //   273: astore_3       
        //   274: aload_3        
        //   275: invokevirtual   java/lang/RuntimeException.getMessage:()Ljava/lang/String;
        //   278: astore_3       
        //   279: new             Ljava/lang/StringBuilder;
        //   282: dup            
        //   283: aload_1        
        //   284: invokestatic    java/lang/String.valueOf:(Ljava/lang/Object;)Ljava/lang/String;
        //   287: invokevirtual   java/lang/String.length:()I
        //   290: bipush          27
        //   292: iadd           
        //   293: aload_3        
        //   294: invokestatic    java/lang/String.valueOf:(Ljava/lang/Object;)Ljava/lang/String;
        //   297: invokevirtual   java/lang/String.length:()I
        //   300: iadd           
        //   301: invokespecial   java/lang/StringBuilder.<init>:(I)V
        //   304: ldc             "Error while pinging URL: "
        //   306: invokevirtual   java/lang/StringBuilder.append:(Ljava/lang/String;)Ljava/lang/StringBuilder;
        //   309: aload_1        
        //   310: invokevirtual   java/lang/StringBuilder.append:(Ljava/lang/String;)Ljava/lang/StringBuilder;
        //   313: ldc             ". "
        //   315: invokevirtual   java/lang/StringBuilder.append:(Ljava/lang/String;)Ljava/lang/StringBuilder;
        //   318: aload_3        
        //   319: invokevirtual   java/lang/StringBuilder.append:(Ljava/lang/String;)Ljava/lang/StringBuilder;
        //   322: invokevirtual   java/lang/StringBuilder.toString:()Ljava/lang/String;
        //   325: invokestatic    com/google/android/gms/internal/ads/zzane.zzdk:(Ljava/lang/String;)V
        //   328: return         
        //    Exceptions:
        //  Try           Handler
        //  Start  End    Start  End    Type                                 
        //  -----  -----  -----  -----  -------------------------------------
        //  0      19     152    208    Ljava/lang/IndexOutOfBoundsException;
        //  0      19     217    273    Ljava/io/IOException;
        //  0      19     273    329    Ljava/lang/RuntimeException;
        //  19     38     152    208    Ljava/lang/IndexOutOfBoundsException;
        //  19     38     217    273    Ljava/io/IOException;
        //  19     38     273    329    Ljava/lang/RuntimeException;
        //  38     79     208    217    Any
        //  93     134    208    217    Any
        //  134    138    152    208    Ljava/lang/IndexOutOfBoundsException;
        //  134    138    217    273    Ljava/io/IOException;
        //  134    138    273    329    Ljava/lang/RuntimeException;
        //  139    149    152    208    Ljava/lang/IndexOutOfBoundsException;
        //  139    149    217    273    Ljava/io/IOException;
        //  139    149    273    329    Ljava/lang/RuntimeException;
        //  210    217    152    208    Ljava/lang/IndexOutOfBoundsException;
        //  210    217    217    273    Ljava/io/IOException;
        //  210    217    273    329    Ljava/lang/RuntimeException;
        // 
        // The error that occurred was:
        // 
        // java.lang.IllegalStateException: Expression is linked from several locations: Label_0093:
        //     at com.strobel.decompiler.ast.Error.expressionLinkedFromMultipleLocations(Error.java:27)
        //     at com.strobel.decompiler.ast.AstOptimizer.mergeDisparateObjectInitializations(AstOptimizer.java:2596)
        //     at com.strobel.decompiler.ast.AstOptimizer.optimize(AstOptimizer.java:235)
        //     at com.strobel.decompiler.ast.AstOptimizer.optimize(AstOptimizer.java:42)
        //     at com.strobel.decompiler.languages.java.ast.AstMethodBodyBuilder.createMethodBody(AstMethodBodyBuilder.java:214)
        //     at com.strobel.decompiler.languages.java.ast.AstMethodBodyBuilder.createMethodBody(AstMethodBodyBuilder.java:99)
        //     at com.strobel.decompiler.languages.java.ast.AstBuilder.createMethodBody(AstBuilder.java:782)
        //     at com.strobel.decompiler.languages.java.ast.AstBuilder.createMethod(AstBuilder.java:675)
        //     at com.strobel.decompiler.languages.java.ast.AstBuilder.addTypeMembers(AstBuilder.java:552)
        //     at com.strobel.decompiler.languages.java.ast.AstBuilder.createTypeCore(AstBuilder.java:519)
        //     at com.strobel.decompiler.languages.java.ast.AstBuilder.createTypeNoCache(AstBuilder.java:161)
        //     at com.strobel.decompiler.languages.java.ast.AstBuilder.createType(AstBuilder.java:150)
        //     at com.strobel.decompiler.languages.java.ast.AstBuilder.addType(AstBuilder.java:125)
        //     at com.strobel.decompiler.languages.java.JavaLanguage.buildAst(JavaLanguage.java:71)
        //     at com.strobel.decompiler.languages.java.JavaLanguage.decompileType(JavaLanguage.java:59)
        //     at com.strobel.decompiler.DecompilerDriver.decompileType(DecompilerDriver.java:330)
        //     at com.strobel.decompiler.DecompilerDriver.decompileJar(DecompilerDriver.java:251)
        //     at com.strobel.decompiler.DecompilerDriver.main(DecompilerDriver.java:126)
        // 
        throw new IllegalStateException("An error occurred while decompiling this method.");
    }
}
