// 
// Decompiled by Procyon v0.5.34
// 

package com.google.android.gms.ads.internal;

import java.util.concurrent.Executor;
import com.google.android.gms.internal.ads.zzaoe;
import com.google.android.gms.internal.ads.zzgk;
import com.google.android.gms.internal.ads.zznk;
import com.google.android.gms.internal.ads.zzkb;
import com.google.android.gms.internal.ads.zzajx;
import com.google.android.gms.internal.ads.zzhx;
import com.google.android.gms.internal.ads.zzadk;
import com.google.android.gms.internal.ads.zzadj;
import com.google.android.gms.internal.ads.zzafa;
import com.google.android.gms.internal.ads.zznx;
import com.google.android.gms.internal.ads.zzrc;
import com.google.android.gms.internal.ads.zzqs;
import com.google.android.gms.internal.ads.zzakk;
import com.google.android.gms.internal.ads.zzhu;
import com.google.android.gms.internal.ads.zzaqw;
import android.os.RemoteException;
import com.google.android.gms.internal.ads.zzakq;
import com.google.android.gms.common.internal.Preconditions;
import com.google.android.gms.internal.ads.zzxg;
import com.google.android.gms.internal.ads.zzakb;
import org.json.JSONException;
import org.json.JSONObject;
import com.google.android.gms.internal.ads.zzajh;
import com.google.android.gms.internal.ads.zzaeg;
import com.google.android.gms.internal.ads.zzajl;
import android.os.Bundle;
import com.google.android.gms.internal.ads.zzjj;
import com.google.android.gms.common.util.VisibleForTesting;
import android.support.annotation.Nullable;
import com.google.android.gms.internal.ads.zzang;
import com.google.android.gms.internal.ads.zzjn;
import android.content.Context;
import com.google.android.gms.internal.ads.zzxn;
import javax.annotation.ParametersAreNonnullByDefault;
import com.google.android.gms.internal.ads.zzadh;
import com.google.android.gms.internal.ads.zzwz;
import com.google.android.gms.ads.internal.overlay.zzn;

@zzadh
@ParametersAreNonnullByDefault
public abstract class zzd extends zza implements zzn, zzbo, zzwz
{
    protected final zzxn zzwh;
    private transient boolean zzwi;
    
    public zzd(final Context context, final zzjn zzjn, final String s, final zzxn zzxn, final zzang zzang, final zzw zzw) {
        this(new zzbw(context, zzjn, s, zzang), zzxn, null, zzw);
    }
    
    @VisibleForTesting
    private zzd(final zzbw zzbw, final zzxn zzwh, @Nullable final zzbl zzbl, final zzw zzw) {
        super(zzbw, null, zzw);
        this.zzwh = zzwh;
        this.zzwi = false;
    }
    
    private final zzaeg zza(final zzjj p0, final Bundle p1, final zzajl p2, final int p3) {
        // 
        // This method could not be decompiled.
        // 
        // Original Bytecode:
        // 
        //     1: getfield        com/google/android/gms/ads/internal/zzd.zzvw:Lcom/google/android/gms/ads/internal/zzbw;
        //     4: getfield        com/google/android/gms/ads/internal/zzbw.zzrt:Landroid/content/Context;
        //     7: invokevirtual   android/content/Context.getApplicationInfo:()Landroid/content/pm/ApplicationInfo;
        //    10: astore          30
        //    12: aload_0        
        //    13: getfield        com/google/android/gms/ads/internal/zzd.zzvw:Lcom/google/android/gms/ads/internal/zzbw;
        //    16: getfield        com/google/android/gms/ads/internal/zzbw.zzrt:Landroid/content/Context;
        //    19: invokestatic    com/google/android/gms/common/wrappers/Wrappers.packageManager:(Landroid/content/Context;)Lcom/google/android/gms/common/wrappers/PackageManagerWrapper;
        //    22: aload           30
        //    24: getfield        android/content/pm/ApplicationInfo.packageName:Ljava/lang/String;
        //    27: iconst_0       
        //    28: invokevirtual   com/google/android/gms/common/wrappers/PackageManagerWrapper.getPackageInfo:(Ljava/lang/String;I)Landroid/content/pm/PackageInfo;
        //    31: astore          26
        //    33: aload_0        
        //    34: getfield        com/google/android/gms/ads/internal/zzd.zzvw:Lcom/google/android/gms/ads/internal/zzbw;
        //    37: getfield        com/google/android/gms/ads/internal/zzbw.zzrt:Landroid/content/Context;
        //    40: invokevirtual   android/content/Context.getResources:()Landroid/content/res/Resources;
        //    43: invokevirtual   android/content/res/Resources.getDisplayMetrics:()Landroid/util/DisplayMetrics;
        //    46: astore          39
        //    48: aconst_null    
        //    49: astore          28
        //    51: aload           28
        //    53: astore          27
        //    55: aload_0        
        //    56: getfield        com/google/android/gms/ads/internal/zzd.zzvw:Lcom/google/android/gms/ads/internal/zzbw;
        //    59: getfield        com/google/android/gms/ads/internal/zzbw.zzacs:Lcom/google/android/gms/ads/internal/zzbx;
        //    62: ifnull          265
        //    65: aload           28
        //    67: astore          27
        //    69: aload_0        
        //    70: getfield        com/google/android/gms/ads/internal/zzd.zzvw:Lcom/google/android/gms/ads/internal/zzbw;
        //    73: getfield        com/google/android/gms/ads/internal/zzbw.zzacs:Lcom/google/android/gms/ads/internal/zzbx;
        //    76: invokevirtual   com/google/android/gms/ads/internal/zzbx.getParent:()Landroid/view/ViewParent;
        //    79: ifnull          265
        //    82: iconst_2       
        //    83: newarray        I
        //    85: astore          27
        //    87: aload_0        
        //    88: getfield        com/google/android/gms/ads/internal/zzd.zzvw:Lcom/google/android/gms/ads/internal/zzbw;
        //    91: getfield        com/google/android/gms/ads/internal/zzbw.zzacs:Lcom/google/android/gms/ads/internal/zzbx;
        //    94: aload           27
        //    96: invokevirtual   com/google/android/gms/ads/internal/zzbx.getLocationOnScreen:([I)V
        //    99: aload           27
        //   101: iconst_0       
        //   102: iaload         
        //   103: istore          9
        //   105: aload           27
        //   107: iconst_1       
        //   108: iaload         
        //   109: istore          10
        //   111: aload_0        
        //   112: getfield        com/google/android/gms/ads/internal/zzd.zzvw:Lcom/google/android/gms/ads/internal/zzbw;
        //   115: getfield        com/google/android/gms/ads/internal/zzbw.zzacs:Lcom/google/android/gms/ads/internal/zzbx;
        //   118: invokevirtual   com/google/android/gms/ads/internal/zzbx.getWidth:()I
        //   121: istore          11
        //   123: aload_0        
        //   124: getfield        com/google/android/gms/ads/internal/zzd.zzvw:Lcom/google/android/gms/ads/internal/zzbw;
        //   127: getfield        com/google/android/gms/ads/internal/zzbw.zzacs:Lcom/google/android/gms/ads/internal/zzbx;
        //   130: invokevirtual   com/google/android/gms/ads/internal/zzbx.getHeight:()I
        //   133: istore          12
        //   135: iconst_0       
        //   136: istore          8
        //   138: iload           8
        //   140: istore          7
        //   142: aload_0        
        //   143: getfield        com/google/android/gms/ads/internal/zzd.zzvw:Lcom/google/android/gms/ads/internal/zzbw;
        //   146: getfield        com/google/android/gms/ads/internal/zzbw.zzacs:Lcom/google/android/gms/ads/internal/zzbx;
        //   149: invokevirtual   com/google/android/gms/ads/internal/zzbx.isShown:()Z
        //   152: ifeq            210
        //   155: iload           8
        //   157: istore          7
        //   159: iload           9
        //   161: iload           11
        //   163: iadd           
        //   164: ifle            210
        //   167: iload           8
        //   169: istore          7
        //   171: iload           10
        //   173: iload           12
        //   175: iadd           
        //   176: ifle            210
        //   179: iload           8
        //   181: istore          7
        //   183: iload           9
        //   185: aload           39
        //   187: getfield        android/util/DisplayMetrics.widthPixels:I
        //   190: if_icmpgt       210
        //   193: iload           8
        //   195: istore          7
        //   197: iload           10
        //   199: aload           39
        //   201: getfield        android/util/DisplayMetrics.heightPixels:I
        //   204: if_icmpgt       210
        //   207: iconst_1       
        //   208: istore          7
        //   210: new             Landroid/os/Bundle;
        //   213: dup            
        //   214: iconst_5       
        //   215: invokespecial   android/os/Bundle.<init>:(I)V
        //   218: astore          27
        //   220: aload           27
        //   222: ldc             "x"
        //   224: iload           9
        //   226: invokevirtual   android/os/Bundle.putInt:(Ljava/lang/String;I)V
        //   229: aload           27
        //   231: ldc             "y"
        //   233: iload           10
        //   235: invokevirtual   android/os/Bundle.putInt:(Ljava/lang/String;I)V
        //   238: aload           27
        //   240: ldc             "width"
        //   242: iload           11
        //   244: invokevirtual   android/os/Bundle.putInt:(Ljava/lang/String;I)V
        //   247: aload           27
        //   249: ldc             "height"
        //   251: iload           12
        //   253: invokevirtual   android/os/Bundle.putInt:(Ljava/lang/String;I)V
        //   256: aload           27
        //   258: ldc             "visible"
        //   260: iload           7
        //   262: invokevirtual   android/os/Bundle.putInt:(Ljava/lang/String;I)V
        //   265: invokestatic    com/google/android/gms/ads/internal/zzbv.zzeo:()Lcom/google/android/gms/internal/ads/zzajm;
        //   268: invokevirtual   com/google/android/gms/internal/ads/zzajm.zzpx:()Lcom/google/android/gms/internal/ads/zzajt;
        //   271: invokevirtual   com/google/android/gms/internal/ads/zzajt.zzql:()Ljava/lang/String;
        //   274: astore          31
        //   276: aload_0        
        //   277: getfield        com/google/android/gms/ads/internal/zzd.zzvw:Lcom/google/android/gms/ads/internal/zzbw;
        //   280: new             Lcom/google/android/gms/internal/ads/zzajj;
        //   283: dup            
        //   284: aload           31
        //   286: aload_0        
        //   287: getfield        com/google/android/gms/ads/internal/zzd.zzvw:Lcom/google/android/gms/ads/internal/zzbw;
        //   290: getfield        com/google/android/gms/ads/internal/zzbw.zzacp:Ljava/lang/String;
        //   293: invokespecial   com/google/android/gms/internal/ads/zzajj.<init>:(Ljava/lang/String;Ljava/lang/String;)V
        //   296: putfield        com/google/android/gms/ads/internal/zzbw.zzacy:Lcom/google/android/gms/internal/ads/zzajj;
        //   299: aload_0        
        //   300: getfield        com/google/android/gms/ads/internal/zzd.zzvw:Lcom/google/android/gms/ads/internal/zzbw;
        //   303: getfield        com/google/android/gms/ads/internal/zzbw.zzacy:Lcom/google/android/gms/internal/ads/zzajj;
        //   306: aload_1        
        //   307: invokevirtual   com/google/android/gms/internal/ads/zzajj.zzn:(Lcom/google/android/gms/internal/ads/zzjj;)V
        //   310: invokestatic    com/google/android/gms/ads/internal/zzbv.zzek:()Lcom/google/android/gms/internal/ads/zzakk;
        //   313: pop            
        //   314: aload_0        
        //   315: getfield        com/google/android/gms/ads/internal/zzd.zzvw:Lcom/google/android/gms/ads/internal/zzbw;
        //   318: getfield        com/google/android/gms/ads/internal/zzbw.zzrt:Landroid/content/Context;
        //   321: aload_0        
        //   322: getfield        com/google/android/gms/ads/internal/zzd.zzvw:Lcom/google/android/gms/ads/internal/zzbw;
        //   325: getfield        com/google/android/gms/ads/internal/zzbw.zzacs:Lcom/google/android/gms/ads/internal/zzbx;
        //   328: aload_0        
        //   329: getfield        com/google/android/gms/ads/internal/zzd.zzvw:Lcom/google/android/gms/ads/internal/zzbw;
        //   332: getfield        com/google/android/gms/ads/internal/zzbw.zzacv:Lcom/google/android/gms/internal/ads/zzjn;
        //   335: invokestatic    com/google/android/gms/internal/ads/zzakk.zza:(Landroid/content/Context;Landroid/view/View;Lcom/google/android/gms/internal/ads/zzjn;)Ljava/lang/String;
        //   338: astore          32
        //   340: lconst_0       
        //   341: lstore          15
        //   343: lload           15
        //   345: lstore          13
        //   347: aload_0        
        //   348: getfield        com/google/android/gms/ads/internal/zzd.zzvw:Lcom/google/android/gms/ads/internal/zzbw;
        //   351: getfield        com/google/android/gms/ads/internal/zzbw.zzadd:Lcom/google/android/gms/internal/ads/zzlg;
        //   354: ifnull          371
        //   357: aload_0        
        //   358: getfield        com/google/android/gms/ads/internal/zzd.zzvw:Lcom/google/android/gms/ads/internal/zzbw;
        //   361: getfield        com/google/android/gms/ads/internal/zzbw.zzadd:Lcom/google/android/gms/internal/ads/zzlg;
        //   364: invokeinterface com/google/android/gms/internal/ads/zzlg.getValue:()J
        //   369: lstore          13
        //   371: invokestatic    java/util/UUID.randomUUID:()Ljava/util/UUID;
        //   374: invokevirtual   java/util/UUID.toString:()Ljava/lang/String;
        //   377: astore          33
        //   379: invokestatic    com/google/android/gms/ads/internal/zzbv.zzep:()Lcom/google/android/gms/internal/ads/zzajv;
        //   382: aload_0        
        //   383: getfield        com/google/android/gms/ads/internal/zzd.zzvw:Lcom/google/android/gms/ads/internal/zzbw;
        //   386: getfield        com/google/android/gms/ads/internal/zzbw.zzrt:Landroid/content/Context;
        //   389: aload_0        
        //   390: aload           31
        //   392: invokevirtual   com/google/android/gms/internal/ads/zzajv.zza:(Landroid/content/Context;Lcom/google/android/gms/internal/ads/zzajs;Ljava/lang/String;)Landroid/os/Bundle;
        //   395: astore          34
        //   397: new             Ljava/util/ArrayList;
        //   400: dup            
        //   401: invokespecial   java/util/ArrayList.<init>:()V
        //   404: astore          35
        //   406: new             Ljava/util/ArrayList;
        //   409: dup            
        //   410: invokespecial   java/util/ArrayList.<init>:()V
        //   413: astore          36
        //   415: iconst_0       
        //   416: istore          7
        //   418: iload           7
        //   420: aload_0        
        //   421: getfield        com/google/android/gms/ads/internal/zzd.zzvw:Lcom/google/android/gms/ads/internal/zzbw;
        //   424: getfield        com/google/android/gms/ads/internal/zzbw.zzadi:Landroid/support/v4/util/SimpleArrayMap;
        //   427: invokevirtual   android/support/v4/util/SimpleArrayMap.size:()I
        //   430: if_icmpge       531
        //   433: aload_0        
        //   434: getfield        com/google/android/gms/ads/internal/zzd.zzvw:Lcom/google/android/gms/ads/internal/zzbw;
        //   437: getfield        com/google/android/gms/ads/internal/zzbw.zzadi:Landroid/support/v4/util/SimpleArrayMap;
        //   440: iload           7
        //   442: invokevirtual   android/support/v4/util/SimpleArrayMap.keyAt:(I)Ljava/lang/Object;
        //   445: checkcast       Ljava/lang/String;
        //   448: astore          28
        //   450: aload           35
        //   452: aload           28
        //   454: invokeinterface java/util/List.add:(Ljava/lang/Object;)Z
        //   459: pop            
        //   460: aload_0        
        //   461: getfield        com/google/android/gms/ads/internal/zzd.zzvw:Lcom/google/android/gms/ads/internal/zzbw;
        //   464: getfield        com/google/android/gms/ads/internal/zzbw.zzadh:Landroid/support/v4/util/SimpleArrayMap;
        //   467: aload           28
        //   469: invokevirtual   android/support/v4/util/SimpleArrayMap.containsKey:(Ljava/lang/Object;)Z
        //   472: ifeq            500
        //   475: aload_0        
        //   476: getfield        com/google/android/gms/ads/internal/zzd.zzvw:Lcom/google/android/gms/ads/internal/zzbw;
        //   479: getfield        com/google/android/gms/ads/internal/zzbw.zzadh:Landroid/support/v4/util/SimpleArrayMap;
        //   482: aload           28
        //   484: invokevirtual   android/support/v4/util/SimpleArrayMap.get:(Ljava/lang/Object;)Ljava/lang/Object;
        //   487: ifnull          500
        //   490: aload           36
        //   492: aload           28
        //   494: invokeinterface java/util/List.add:(Ljava/lang/Object;)Z
        //   499: pop            
        //   500: iload           7
        //   502: iconst_1       
        //   503: iadd           
        //   504: istore          7
        //   506: goto            418
        //   509: astore          26
        //   511: aconst_null    
        //   512: astore          26
        //   514: goto            33
        //   517: astore          28
        //   519: ldc             "Cannot get correlation id, default to 0."
        //   521: invokestatic    com/google/android/gms/internal/ads/zzakb.zzdk:(Ljava/lang/String;)V
        //   524: lload           15
        //   526: lstore          13
        //   528: goto            371
        //   531: new             Lcom/google/android/gms/ads/internal/zzg;
        //   534: dup            
        //   535: aload_0        
        //   536: invokespecial   com/google/android/gms/ads/internal/zzg.<init>:(Lcom/google/android/gms/ads/internal/zzd;)V
        //   539: invokestatic    com/google/android/gms/internal/ads/zzaki.zza:(Ljava/util/concurrent/Callable;)Lcom/google/android/gms/internal/ads/zzanz;
        //   542: astore          37
        //   544: new             Lcom/google/android/gms/ads/internal/zzh;
        //   547: dup            
        //   548: aload_0        
        //   549: invokespecial   com/google/android/gms/ads/internal/zzh.<init>:(Lcom/google/android/gms/ads/internal/zzd;)V
        //   552: invokestatic    com/google/android/gms/internal/ads/zzaki.zza:(Ljava/util/concurrent/Callable;)Lcom/google/android/gms/internal/ads/zzanz;
        //   555: astore          38
        //   557: aconst_null    
        //   558: astore          28
        //   560: aload_3        
        //   561: ifnull          570
        //   564: aload_3        
        //   565: invokevirtual   com/google/android/gms/internal/ads/zzajl.zzpu:()Ljava/lang/String;
        //   568: astore          28
        //   570: aconst_null    
        //   571: astore          29
        //   573: aload           29
        //   575: astore_3       
        //   576: aload_0        
        //   577: getfield        com/google/android/gms/ads/internal/zzd.zzvw:Lcom/google/android/gms/ads/internal/zzbw;
        //   580: getfield        com/google/android/gms/ads/internal/zzbw.zzads:Ljava/util/List;
        //   583: ifnull          656
        //   586: aload           29
        //   588: astore_3       
        //   589: aload_0        
        //   590: getfield        com/google/android/gms/ads/internal/zzd.zzvw:Lcom/google/android/gms/ads/internal/zzbw;
        //   593: getfield        com/google/android/gms/ads/internal/zzbw.zzads:Ljava/util/List;
        //   596: invokeinterface java/util/List.size:()I
        //   601: ifle            656
        //   604: iconst_0       
        //   605: istore          7
        //   607: aload           26
        //   609: ifnull          619
        //   612: aload           26
        //   614: getfield        android/content/pm/PackageInfo.versionCode:I
        //   617: istore          7
        //   619: iload           7
        //   621: invokestatic    com/google/android/gms/ads/internal/zzbv.zzeo:()Lcom/google/android/gms/internal/ads/zzajm;
        //   624: invokevirtual   com/google/android/gms/internal/ads/zzajm.zzqh:()Lcom/google/android/gms/internal/ads/zzakd;
        //   627: invokevirtual   com/google/android/gms/internal/ads/zzakd.zzqz:()I
        //   630: if_icmple       1065
        //   633: invokestatic    com/google/android/gms/ads/internal/zzbv.zzeo:()Lcom/google/android/gms/internal/ads/zzajm;
        //   636: invokevirtual   com/google/android/gms/internal/ads/zzajm.zzqh:()Lcom/google/android/gms/internal/ads/zzakd;
        //   639: invokevirtual   com/google/android/gms/internal/ads/zzakd.zzrf:()V
        //   642: invokestatic    com/google/android/gms/ads/internal/zzbv.zzeo:()Lcom/google/android/gms/internal/ads/zzajm;
        //   645: invokevirtual   com/google/android/gms/internal/ads/zzajm.zzqh:()Lcom/google/android/gms/internal/ads/zzakd;
        //   648: iload           7
        //   650: invokevirtual   com/google/android/gms/internal/ads/zzakd.zzae:(I)V
        //   653: aload           29
        //   655: astore_3       
        //   656: aload_0        
        //   657: getfield        com/google/android/gms/ads/internal/zzd.zzvw:Lcom/google/android/gms/ads/internal/zzbw;
        //   660: getfield        com/google/android/gms/ads/internal/zzbw.zzacv:Lcom/google/android/gms/internal/ads/zzjn;
        //   663: astore          29
        //   665: aload_0        
        //   666: getfield        com/google/android/gms/ads/internal/zzd.zzvw:Lcom/google/android/gms/ads/internal/zzbw;
        //   669: getfield        com/google/android/gms/ads/internal/zzbw.zzacp:Ljava/lang/String;
        //   672: astore          40
        //   674: invokestatic    com/google/android/gms/internal/ads/zzkb.zzih:()Ljava/lang/String;
        //   677: astore          41
        //   679: aload_0        
        //   680: getfield        com/google/android/gms/ads/internal/zzd.zzvw:Lcom/google/android/gms/ads/internal/zzbw;
        //   683: getfield        com/google/android/gms/ads/internal/zzbw.zzacr:Lcom/google/android/gms/internal/ads/zzang;
        //   686: astore          42
        //   688: aload_0        
        //   689: getfield        com/google/android/gms/ads/internal/zzd.zzvw:Lcom/google/android/gms/ads/internal/zzbw;
        //   692: getfield        com/google/android/gms/ads/internal/zzbw.zzads:Ljava/util/List;
        //   695: astore          43
        //   697: invokestatic    com/google/android/gms/ads/internal/zzbv.zzeo:()Lcom/google/android/gms/internal/ads/zzajm;
        //   700: invokevirtual   com/google/android/gms/internal/ads/zzajm.zzqh:()Lcom/google/android/gms/internal/ads/zzakd;
        //   703: invokevirtual   com/google/android/gms/internal/ads/zzakd.zzqt:()Z
        //   706: istore          17
        //   708: aload           39
        //   710: getfield        android/util/DisplayMetrics.widthPixels:I
        //   713: istore          7
        //   715: aload           39
        //   717: getfield        android/util/DisplayMetrics.heightPixels:I
        //   720: istore          8
        //   722: aload           39
        //   724: getfield        android/util/DisplayMetrics.density:F
        //   727: fstore          5
        //   729: invokestatic    com/google/android/gms/internal/ads/zznk.zzjb:()Ljava/util/List;
        //   732: astore          39
        //   734: aload_0        
        //   735: getfield        com/google/android/gms/ads/internal/zzd.zzvw:Lcom/google/android/gms/ads/internal/zzbw;
        //   738: getfield        com/google/android/gms/ads/internal/zzbw.zzaco:Ljava/lang/String;
        //   741: astore          44
        //   743: aload_0        
        //   744: getfield        com/google/android/gms/ads/internal/zzd.zzvw:Lcom/google/android/gms/ads/internal/zzbw;
        //   747: getfield        com/google/android/gms/ads/internal/zzbw.zzadj:Lcom/google/android/gms/internal/ads/zzpl;
        //   750: astore          45
        //   752: aload_0        
        //   753: getfield        com/google/android/gms/ads/internal/zzd.zzvw:Lcom/google/android/gms/ads/internal/zzbw;
        //   756: invokevirtual   com/google/android/gms/ads/internal/zzbw.zzfq:()Ljava/lang/String;
        //   759: astore          46
        //   761: invokestatic    com/google/android/gms/ads/internal/zzbv.zzfj:()Lcom/google/android/gms/internal/ads/zzalb;
        //   764: invokevirtual   com/google/android/gms/internal/ads/zzalb.zzdo:()F
        //   767: fstore          6
        //   769: invokestatic    com/google/android/gms/ads/internal/zzbv.zzfj:()Lcom/google/android/gms/internal/ads/zzalb;
        //   772: invokevirtual   com/google/android/gms/internal/ads/zzalb.zzdp:()Z
        //   775: istore          18
        //   777: invokestatic    com/google/android/gms/ads/internal/zzbv.zzek:()Lcom/google/android/gms/internal/ads/zzakk;
        //   780: pop            
        //   781: aload_0        
        //   782: getfield        com/google/android/gms/ads/internal/zzd.zzvw:Lcom/google/android/gms/ads/internal/zzbw;
        //   785: getfield        com/google/android/gms/ads/internal/zzbw.zzrt:Landroid/content/Context;
        //   788: invokestatic    com/google/android/gms/internal/ads/zzakk.zzas:(Landroid/content/Context;)I
        //   791: istore          9
        //   793: invokestatic    com/google/android/gms/ads/internal/zzbv.zzek:()Lcom/google/android/gms/internal/ads/zzakk;
        //   796: pop            
        //   797: aload_0        
        //   798: getfield        com/google/android/gms/ads/internal/zzd.zzvw:Lcom/google/android/gms/ads/internal/zzbw;
        //   801: getfield        com/google/android/gms/ads/internal/zzbw.zzacs:Lcom/google/android/gms/ads/internal/zzbx;
        //   804: invokestatic    com/google/android/gms/internal/ads/zzakk.zzx:(Landroid/view/View;)I
        //   807: istore          10
        //   809: aload_0        
        //   810: getfield        com/google/android/gms/ads/internal/zzd.zzvw:Lcom/google/android/gms/ads/internal/zzbw;
        //   813: getfield        com/google/android/gms/ads/internal/zzbw.zzrt:Landroid/content/Context;
        //   816: instanceof      Landroid/app/Activity;
        //   819: istore          19
        //   821: invokestatic    com/google/android/gms/ads/internal/zzbv.zzeo:()Lcom/google/android/gms/internal/ads/zzajm;
        //   824: invokevirtual   com/google/android/gms/internal/ads/zzajm.zzqh:()Lcom/google/android/gms/internal/ads/zzakd;
        //   827: invokevirtual   com/google/android/gms/internal/ads/zzakd.zzqy:()Z
        //   830: istore          20
        //   832: invokestatic    com/google/android/gms/ads/internal/zzbv.zzeo:()Lcom/google/android/gms/internal/ads/zzajm;
        //   835: invokevirtual   com/google/android/gms/internal/ads/zzajm.zzqa:()Z
        //   838: istore          21
        //   840: invokestatic    com/google/android/gms/ads/internal/zzbv.zzff:()Lcom/google/android/gms/internal/ads/zzaqg;
        //   843: invokevirtual   com/google/android/gms/internal/ads/zzaqg.zztx:()I
        //   846: istore          11
        //   848: invokestatic    com/google/android/gms/ads/internal/zzbv.zzek:()Lcom/google/android/gms/internal/ads/zzakk;
        //   851: pop            
        //   852: invokestatic    com/google/android/gms/internal/ads/zzakk.zzrk:()Landroid/os/Bundle;
        //   855: astore          47
        //   857: invokestatic    com/google/android/gms/ads/internal/zzbv.zzeu:()Lcom/google/android/gms/internal/ads/zzalk;
        //   860: invokevirtual   com/google/android/gms/internal/ads/zzalk.zzrw:()Ljava/lang/String;
        //   863: astore          48
        //   865: aload_0        
        //   866: getfield        com/google/android/gms/ads/internal/zzd.zzvw:Lcom/google/android/gms/ads/internal/zzbw;
        //   869: getfield        com/google/android/gms/ads/internal/zzbw.zzadl:Lcom/google/android/gms/internal/ads/zzlu;
        //   872: astore          49
        //   874: invokestatic    com/google/android/gms/ads/internal/zzbv.zzeu:()Lcom/google/android/gms/internal/ads/zzalk;
        //   877: invokevirtual   com/google/android/gms/internal/ads/zzalk.zzrx:()Z
        //   880: istore          22
        //   882: invokestatic    com/google/android/gms/internal/ads/zzua.zzlk:()Lcom/google/android/gms/internal/ads/zzua;
        //   885: invokevirtual   com/google/android/gms/internal/ads/zzua.zzlt:()Landroid/os/Bundle;
        //   888: astore          50
        //   890: invokestatic    com/google/android/gms/ads/internal/zzbv.zzeo:()Lcom/google/android/gms/internal/ads/zzajm;
        //   893: invokevirtual   com/google/android/gms/internal/ads/zzajm.zzqh:()Lcom/google/android/gms/internal/ads/zzakd;
        //   896: aload_0        
        //   897: getfield        com/google/android/gms/ads/internal/zzd.zzvw:Lcom/google/android/gms/ads/internal/zzbw;
        //   900: getfield        com/google/android/gms/ads/internal/zzbw.zzacp:Ljava/lang/String;
        //   903: invokevirtual   com/google/android/gms/internal/ads/zzakd.zzcr:(Ljava/lang/String;)Z
        //   906: istore          23
        //   908: aload_0        
        //   909: getfield        com/google/android/gms/ads/internal/zzd.zzvw:Lcom/google/android/gms/ads/internal/zzbw;
        //   912: getfield        com/google/android/gms/ads/internal/zzbw.zzadn:Ljava/util/List;
        //   915: astore          51
        //   917: aload_0        
        //   918: getfield        com/google/android/gms/ads/internal/zzd.zzvw:Lcom/google/android/gms/ads/internal/zzbw;
        //   921: getfield        com/google/android/gms/ads/internal/zzbw.zzrt:Landroid/content/Context;
        //   924: invokestatic    com/google/android/gms/common/wrappers/Wrappers.packageManager:(Landroid/content/Context;)Lcom/google/android/gms/common/wrappers/PackageManagerWrapper;
        //   927: invokevirtual   com/google/android/gms/common/wrappers/PackageManagerWrapper.isCallerInstantApp:()Z
        //   930: istore          24
        //   932: invokestatic    com/google/android/gms/ads/internal/zzbv.zzeo:()Lcom/google/android/gms/internal/ads/zzajm;
        //   935: invokevirtual   com/google/android/gms/internal/ads/zzajm.zzqb:()Z
        //   938: istore          25
        //   940: invokestatic    com/google/android/gms/ads/internal/zzbv.zzem:()Lcom/google/android/gms/internal/ads/zzakq;
        //   943: pop            
        //   944: new             Lcom/google/android/gms/internal/ads/zzaeg;
        //   947: dup            
        //   948: aload           27
        //   950: aload_1        
        //   951: aload           29
        //   953: aload           40
        //   955: aload           30
        //   957: aload           26
        //   959: aload           31
        //   961: aload           41
        //   963: aload           42
        //   965: aload           34
        //   967: aload           43
        //   969: aload           35
        //   971: aload_2        
        //   972: iload           17
        //   974: iload           7
        //   976: iload           8
        //   978: fload           5
        //   980: aload           32
        //   982: lload           13
        //   984: aload           33
        //   986: aload           39
        //   988: aload           44
        //   990: aload           45
        //   992: aload           46
        //   994: fload           6
        //   996: iload           18
        //   998: iload           9
        //  1000: iload           10
        //  1002: iload           19
        //  1004: iload           20
        //  1006: aload           37
        //  1008: aload           28
        //  1010: iload           21
        //  1012: iload           11
        //  1014: aload           47
        //  1016: aload           48
        //  1018: aload           49
        //  1020: iload           22
        //  1022: aload           50
        //  1024: iload           23
        //  1026: aload           38
        //  1028: aload           51
        //  1030: aload_3        
        //  1031: aload           36
        //  1033: iload           4
        //  1035: iload           24
        //  1037: iload           25
        //  1039: invokestatic    com/google/android/gms/internal/ads/zzakq.zzrp:()Z
        //  1042: invokestatic    com/google/android/gms/ads/internal/zzbv.zzeo:()Lcom/google/android/gms/internal/ads/zzajm;
        //  1045: invokevirtual   com/google/android/gms/internal/ads/zzajm.zzqi:()Lcom/google/android/gms/internal/ads/zzanz;
        //  1048: aconst_null    
        //  1049: ldc2_w          1000
        //  1052: getstatic       java/util/concurrent/TimeUnit.MILLISECONDS:Ljava/util/concurrent/TimeUnit;
        //  1055: invokestatic    com/google/android/gms/internal/ads/zzano.zza:(Ljava/util/concurrent/Future;Ljava/lang/Object;JLjava/util/concurrent/TimeUnit;)Ljava/lang/Object;
        //  1058: checkcast       Ljava/util/ArrayList;
        //  1061: invokespecial   com/google/android/gms/internal/ads/zzaeg.<init>:(Landroid/os/Bundle;Lcom/google/android/gms/internal/ads/zzjj;Lcom/google/android/gms/internal/ads/zzjn;Ljava/lang/String;Landroid/content/pm/ApplicationInfo;Landroid/content/pm/PackageInfo;Ljava/lang/String;Ljava/lang/String;Lcom/google/android/gms/internal/ads/zzang;Landroid/os/Bundle;Ljava/util/List;Ljava/util/List;Landroid/os/Bundle;ZIIFLjava/lang/String;JLjava/lang/String;Ljava/util/List;Ljava/lang/String;Lcom/google/android/gms/internal/ads/zzpl;Ljava/lang/String;FZIIZZLjava/util/concurrent/Future;Ljava/lang/String;ZILandroid/os/Bundle;Ljava/lang/String;Lcom/google/android/gms/internal/ads/zzlu;ZLandroid/os/Bundle;ZLjava/util/concurrent/Future;Ljava/util/List;Ljava/lang/String;Ljava/util/List;IZZZLjava/util/ArrayList;)V
        //  1064: areturn        
        //  1065: invokestatic    com/google/android/gms/ads/internal/zzbv.zzeo:()Lcom/google/android/gms/internal/ads/zzajm;
        //  1068: invokevirtual   com/google/android/gms/internal/ads/zzajm.zzqh:()Lcom/google/android/gms/internal/ads/zzakd;
        //  1071: invokevirtual   com/google/android/gms/internal/ads/zzakd.zzre:()Lorg/json/JSONObject;
        //  1074: astore          40
        //  1076: aload           29
        //  1078: astore_3       
        //  1079: aload           40
        //  1081: ifnull          656
        //  1084: aload           40
        //  1086: aload_0        
        //  1087: getfield        com/google/android/gms/ads/internal/zzd.zzvw:Lcom/google/android/gms/ads/internal/zzbw;
        //  1090: getfield        com/google/android/gms/ads/internal/zzbw.zzacp:Ljava/lang/String;
        //  1093: invokevirtual   org/json/JSONObject.optJSONArray:(Ljava/lang/String;)Lorg/json/JSONArray;
        //  1096: astore          40
        //  1098: aload           29
        //  1100: astore_3       
        //  1101: aload           40
        //  1103: ifnull          656
        //  1106: aload           40
        //  1108: invokevirtual   org/json/JSONArray.toString:()Ljava/lang/String;
        //  1111: astore_3       
        //  1112: goto            656
        //    Exceptions:
        //  Try           Handler
        //  Start  End    Start  End    Type                                                     
        //  -----  -----  -----  -----  ---------------------------------------------------------
        //  12     33     509    517    Landroid/content/pm/PackageManager$NameNotFoundException;
        //  357    371    517    531    Landroid/os/RemoteException;
        // 
        // The error that occurred was:
        // 
        // java.lang.IllegalStateException: Expression is linked from several locations: Label_0371:
        //     at com.strobel.decompiler.ast.Error.expressionLinkedFromMultipleLocations(Error.java:27)
        //     at com.strobel.decompiler.ast.AstOptimizer.mergeDisparateObjectInitializations(AstOptimizer.java:2596)
        //     at com.strobel.decompiler.ast.AstOptimizer.optimize(AstOptimizer.java:235)
        //     at com.strobel.decompiler.ast.AstOptimizer.optimize(AstOptimizer.java:42)
        //     at com.strobel.decompiler.languages.java.ast.AstMethodBodyBuilder.createMethodBody(AstMethodBodyBuilder.java:214)
        //     at com.strobel.decompiler.languages.java.ast.AstMethodBodyBuilder.createMethodBody(AstMethodBodyBuilder.java:99)
        //     at com.strobel.decompiler.languages.java.ast.AstBuilder.createMethodBody(AstBuilder.java:782)
        //     at com.strobel.decompiler.languages.java.ast.AstBuilder.createMethod(AstBuilder.java:675)
        //     at com.strobel.decompiler.languages.java.ast.AstBuilder.addTypeMembers(AstBuilder.java:552)
        //     at com.strobel.decompiler.languages.java.ast.AstBuilder.createTypeCore(AstBuilder.java:519)
        //     at com.strobel.decompiler.languages.java.ast.AstBuilder.createTypeNoCache(AstBuilder.java:161)
        //     at com.strobel.decompiler.languages.java.ast.AstBuilder.createType(AstBuilder.java:150)
        //     at com.strobel.decompiler.languages.java.ast.AstBuilder.addType(AstBuilder.java:125)
        //     at com.strobel.decompiler.languages.java.JavaLanguage.buildAst(JavaLanguage.java:71)
        //     at com.strobel.decompiler.languages.java.JavaLanguage.decompileType(JavaLanguage.java:59)
        //     at com.strobel.decompiler.DecompilerDriver.decompileType(DecompilerDriver.java:330)
        //     at com.strobel.decompiler.DecompilerDriver.decompileJar(DecompilerDriver.java:251)
        //     at com.strobel.decompiler.DecompilerDriver.main(DecompilerDriver.java:126)
        // 
        throw new IllegalStateException("An error occurred while decompiling this method.");
    }
    
    @Nullable
    static String zzc(final zzajh zzajh) {
        String s = null;
        if (zzajh == null) {
            s = null;
        }
        else {
            final String zzbty = zzajh.zzbty;
            Label_0075: {
                if (!"com.google.android.gms.ads.mediation.customevent.CustomEventAdapter".equals(zzbty) && !"com.google.ads.mediation.customevent.CustomEventAdapter".equals(zzbty)) {
                    break Label_0075;
                }
                int n = 1;
                while (true) {
                    s = zzbty;
                    if (n == 0) {
                        return s;
                    }
                    s = zzbty;
                    if (zzajh.zzbtw == null) {
                        return s;
                    }
                    final String zzbsb = zzajh.zzbtw.zzbsb;
                    try {
                        return new JSONObject(zzbsb).getString("class_name");
                        n = 0;
                        continue;
                    }
                    catch (NullPointerException ex) {
                        return zzbty;
                    }
                    catch (JSONException ex2) {
                        return zzbty;
                    }
                    break;
                }
            }
        }
        return s;
    }
    
    @Nullable
    public final String getMediationAdapterClassName() {
        if (this.zzvw.zzacw == null) {
            return null;
        }
        return this.zzvw.zzacw.zzbty;
    }
    
    @Override
    public void onAdClicked() {
        if (this.zzvw.zzacw == null) {
            zzakb.zzdk("Ad state was null when trying to ping click URLs.");
            return;
        }
        if (this.zzvw.zzacw.zzcod != null && this.zzvw.zzacw.zzcod.zzbsn != null) {
            zzbv.zzfd();
            zzxg.zza(this.zzvw.zzrt, this.zzvw.zzacr.zzcw, this.zzvw.zzacw, this.zzvw.zzacp, false, this.zzc(this.zzvw.zzacw.zzcod.zzbsn));
        }
        if (this.zzvw.zzacw.zzbtw != null && this.zzvw.zzacw.zzbtw.zzbrw != null) {
            zzbv.zzfd();
            zzxg.zza(this.zzvw.zzrt, this.zzvw.zzacr.zzcw, this.zzvw.zzacw, this.zzvw.zzacp, false, this.zzvw.zzacw.zzbtw.zzbrw);
        }
        super.onAdClicked();
    }
    
    @Override
    public final void onPause() {
        this.zzvy.zzj(this.zzvw.zzacw);
    }
    
    @Override
    public final void onResume() {
        this.zzvy.zzk(this.zzvw.zzacw);
    }
    
    @Override
    public void pause() {
        Preconditions.checkMainThread("pause must be called on the main UI thread.");
        if (this.zzvw.zzacw != null && this.zzvw.zzacw.zzbyo != null && this.zzvw.zzfo()) {
            zzbv.zzem();
            zzakq.zzi(this.zzvw.zzacw.zzbyo);
        }
        while (true) {
            if (this.zzvw.zzacw == null || this.zzvw.zzacw.zzbtx == null) {
                break Label_0095;
            }
            try {
                this.zzvw.zzacw.zzbtx.pause();
                this.zzvy.zzj(this.zzvw.zzacw);
                this.zzvv.pause();
            }
            catch (RemoteException ex) {
                zzakb.zzdk("Could not pause mediation adapter.");
                continue;
            }
            break;
        }
    }
    
    public final void recordImpression() {
        this.zza(this.zzvw.zzacw, false);
    }
    
    @Override
    public void resume() {
        Preconditions.checkMainThread("resume must be called on the main UI thread.");
        zzaqw zzbyo;
        final zzaqw zzaqw = zzbyo = null;
        if (this.zzvw.zzacw != null) {
            zzbyo = zzaqw;
            if (this.zzvw.zzacw.zzbyo != null) {
                zzbyo = this.zzvw.zzacw.zzbyo;
            }
        }
        if (zzbyo != null && this.zzvw.zzfo()) {
            zzbv.zzem();
            zzakq.zzj(this.zzvw.zzacw.zzbyo);
        }
        while (true) {
            if (this.zzvw.zzacw == null || this.zzvw.zzacw.zzbtx == null) {
                break Label_0116;
            }
            try {
                this.zzvw.zzacw.zzbtx.resume();
                if (zzbyo == null || !zzbyo.zzum()) {
                    this.zzvv.resume();
                }
                this.zzvy.zzk(this.zzvw.zzacw);
            }
            catch (RemoteException ex) {
                zzakb.zzdk("Could not resume mediation adapter.");
                continue;
            }
            break;
        }
    }
    
    public void showInterstitial() {
        zzakb.zzdk("showInterstitial is not supported for current ad type");
    }
    
    protected void zza(@Nullable final zzajh zzajh, final boolean b) {
        if (zzajh == null) {
            zzakb.zzdk("Ad state was null when trying to ping impression URLs.");
        }
        else {
            if (zzajh == null) {
                zzakb.zzdk("Ad state was null when trying to ping impression URLs.");
            }
            else {
                zzakb.zzck("Pinging Impression URLs.");
                if (super.zzvw.zzacy != null) {
                    super.zzvw.zzacy.zzpm();
                }
                zzajh.zzcoq.zza(zzhu.zza.zzb.zzakn);
                if (zzajh.zzbso != null && !zzajh.zzcok) {
                    zzbv.zzek();
                    zzakk.zza(super.zzvw.zzrt, super.zzvw.zzacr.zzcw, this.zzc(zzajh.zzbso));
                    zzajh.zzcok = true;
                }
            }
            if (!zzajh.zzcom || b) {
                if (zzajh.zzcod != null && zzajh.zzcod.zzbso != null) {
                    zzbv.zzfd();
                    zzxg.zza(this.zzvw.zzrt, this.zzvw.zzacr.zzcw, zzajh, this.zzvw.zzacp, b, this.zzc(zzajh.zzcod.zzbso));
                }
                if (zzajh.zzbtw != null && zzajh.zzbtw.zzbrx != null) {
                    zzbv.zzfd();
                    zzxg.zza(this.zzvw.zzrt, this.zzvw.zzacr.zzcw, zzajh, this.zzvw.zzacp, b, zzajh.zzbtw.zzbrx);
                }
                zzajh.zzcom = true;
            }
        }
    }
    
    @Override
    public final void zza(final zzqs zzqs, final String s) {
        final zzrc zzrc = null;
        while (true) {
            Label_0083: {
                if (zzqs == null) {
                    break Label_0083;
                }
                try {
                    final String customTemplateId = zzqs.getCustomTemplateId();
                    zzrc zzrc2 = zzrc;
                    if (this.zzvw.zzadh != null) {
                        zzrc2 = zzrc;
                        if (customTemplateId != null) {
                            zzrc2 = (zzrc)this.zzvw.zzadh.get((Object)customTemplateId);
                        }
                    }
                    if (zzrc2 == null) {
                        zzakb.zzdk("Mediation adapter invoked onCustomClick but no listeners were set.");
                        return;
                    }
                    zzrc2.zzb(zzqs, s);
                    return;
                }
                catch (RemoteException ex) {
                    zzakb.zzc("Unable to call onCustomClick.", (Throwable)ex);
                    return;
                }
            }
            final String customTemplateId = null;
            continue;
        }
    }
    
    public final boolean zza(final zzaeg zzaeg, final zznx zzvr) {
        (this.zzvr = zzvr).zze("seq_num", zzaeg.zzccy);
        zzvr.zze("request_id", zzaeg.zzcdi);
        zzvr.zze("session_id", zzaeg.zzccz);
        if (zzaeg.zzccw != null) {
            zzvr.zze("app_version", String.valueOf(zzaeg.zzccw.versionCode));
        }
        final zzbw zzvw = this.zzvw;
        zzbv.zzeg();
        final Context zzrt = this.zzvw.zzrt;
        final zzhx zzxb = this.zzwc.zzxb;
        zzajx zzact;
        if (zzaeg.zzccv.extras.getBundle("sdk_less_server_data") != null) {
            zzact = new zzafa(zzrt, zzaeg, this, zzxb);
        }
        else {
            zzact = new zzadk(zzrt, zzaeg, this, zzxb);
        }
        zzact.zzqo();
        zzvw.zzact = zzact;
        return true;
    }
    
    @Override
    final boolean zza(final zzajh zzajh) {
        boolean boolean1 = false;
        zzjj zzjj;
        if (this.zzvx != null) {
            zzjj = this.zzvx;
            this.zzvx = null;
        }
        else {
            final zzjj zzjj2 = zzjj = zzajh.zzccv;
            if (zzjj2.extras != null) {
                boolean1 = zzjj2.extras.getBoolean("_noRefresh", false);
                zzjj = zzjj2;
            }
        }
        return this.zza(zzjj, zzajh, boolean1);
    }
    
    @Override
    protected boolean zza(@Nullable final zzajh zzajh, final zzajh zzajh2) {
        int zzbtd = 0;
        if (zzajh != null && zzajh.zzbtz != null) {
            zzajh.zzbtz.zza((zzwz)null);
        }
        if (zzajh2.zzbtz != null) {
            zzajh2.zzbtz.zza(this);
        }
        int zzbtc;
        if (zzajh2.zzcod != null) {
            zzbtc = zzajh2.zzcod.zzbtc;
            zzbtd = zzajh2.zzcod.zzbtd;
        }
        else {
            zzbtc = 0;
        }
        this.zzvw.zzadt.zze(zzbtc, zzbtd);
        return true;
    }
    
    protected boolean zza(final zzjj zzjj, final zzajh zzajh, final boolean b) {
        if (!b && this.zzvw.zzfo()) {
            if (zzajh.zzbsu > 0L) {
                this.zzvv.zza(zzjj, zzajh.zzbsu);
            }
            else if (zzajh.zzcod != null && zzajh.zzcod.zzbsu > 0L) {
                this.zzvv.zza(zzjj, zzajh.zzcod.zzbsu);
            }
            else if (!zzajh.zzceq && zzajh.errorCode == 2) {
                this.zzvv.zzg(zzjj);
            }
        }
        return this.zzvv.zzdz();
    }
    
    public boolean zza(final zzjj zzjj, final zznx zznx) {
        return this.zza(zzjj, zznx, 1);
    }
    
    public final boolean zza(final zzjj zzjj, final zznx zznx, final int n) {
        if (!this.zzca()) {
            return false;
        }
        zzbv.zzek();
        final zzgk zzaf = zzbv.zzeo().zzaf(this.zzvw.zzrt);
        Bundle zza;
        if (zzaf == null) {
            zza = null;
        }
        else {
            zza = zzakk.zza(zzaf);
        }
        this.zzvv.cancel();
        this.zzvw.zzadv = 0;
        zzajl zzajl;
        if (zzkb.zzik().zzd(zznk.zzbcs)) {
            final zzajl zzra = zzbv.zzeo().zzqh().zzra();
            final zzad zzes = zzbv.zzes();
            final Context zzrt = this.zzvw.zzrt;
            final zzang zzacr = this.zzvw.zzacr;
            final String zzacp = this.zzvw.zzacp;
            String zzpv;
            if (zzra != null) {
                zzpv = zzra.zzpv();
            }
            else {
                zzpv = null;
            }
            zzes.zza(zzrt, zzacr, false, zzra, zzpv, zzacp, null);
            zzajl = zzra;
        }
        else {
            zzajl = null;
        }
        return this.zza(this.zza(zzjj, zza, zzajl, n), zznx);
    }
    
    @Override
    public final void zzb(final zzajh zzajh) {
        super.zzb(zzajh);
        if (zzajh.zzbtw != null) {
            zzakb.zzck("Disable the debug gesture detector on the mediation ad frame.");
            if (this.zzvw.zzacs != null) {
                this.zzvw.zzacs.zzfu();
            }
            zzakb.zzck("Pinging network fill URLs.");
            zzbv.zzfd();
            zzxg.zza(this.zzvw.zzrt, this.zzvw.zzacr.zzcw, zzajh, this.zzvw.zzacp, false, zzajh.zzbtw.zzbsa);
            if (zzajh.zzcod != null && zzajh.zzcod.zzbsr != null && zzajh.zzcod.zzbsr.size() > 0) {
                zzakb.zzck("Pinging urls remotely");
                zzbv.zzek().zza(this.zzvw.zzrt, zzajh.zzcod.zzbsr);
            }
        }
        else {
            zzakb.zzck("Enable the debug gesture detector on the admob ad frame.");
            if (this.zzvw.zzacs != null) {
                this.zzvw.zzacs.zzft();
            }
        }
        if (zzajh.errorCode == 3 && zzajh.zzcod != null && zzajh.zzcod.zzbsq != null) {
            zzakb.zzck("Pinging no fill URLs.");
            zzbv.zzfd();
            zzxg.zza(this.zzvw.zzrt, this.zzvw.zzacr.zzcw, zzajh, this.zzvw.zzacp, false, zzajh.zzcod.zzbsq);
        }
    }
    
    protected final void zzb(@Nullable final zzajh zzajh, final boolean b) {
        if (zzajh != null) {
            if (zzajh != null && zzajh.zzbsp != null && !zzajh.zzcol) {
                zzbv.zzek();
                zzakk.zza(super.zzvw.zzrt, super.zzvw.zzacr.zzcw, this.zzb(zzajh.zzbsp));
                zzajh.zzcol = true;
            }
            if (!zzajh.zzcon || b) {
                if (zzajh.zzcod != null && zzajh.zzcod.zzbsp != null) {
                    zzbv.zzfd();
                    zzxg.zza(this.zzvw.zzrt, this.zzvw.zzacr.zzcw, zzajh, this.zzvw.zzacp, b, this.zzb(zzajh.zzcod.zzbsp));
                }
                if (zzajh.zzbtw != null && zzajh.zzbtw.zzbry != null) {
                    zzbv.zzfd();
                    zzxg.zza(this.zzvw.zzrt, this.zzvw.zzacr.zzcw, zzajh, this.zzvw.zzacp, b, zzajh.zzbtw.zzbry);
                }
                zzajh.zzcon = true;
            }
        }
    }
    
    @Override
    public final void zzb(final String s, final String s2) {
        this.onAppEvent(s, s2);
    }
    
    @Override
    protected final boolean zzc(final zzjj zzjj) {
        return super.zzc(zzjj) && !this.zzwi;
    }
    
    protected boolean zzca() {
        boolean b = true;
        zzbv.zzek();
        if (zzakk.zzl(this.zzvw.zzrt, "android.permission.INTERNET")) {
            zzbv.zzek();
            if (zzakk.zzaj(this.zzvw.zzrt)) {
                return b;
            }
        }
        b = false;
        return b;
    }
    
    @Override
    public void zzcb() {
        this.zzwi = false;
        this.zzbn();
        this.zzvw.zzacy.zzpo();
    }
    
    @Override
    public void zzcc() {
        this.zzwi = true;
        this.zzbp();
    }
    
    @Override
    public void zzcd() {
        zzakb.zzdk("Mediated ad does not support onVideoEnd callback");
    }
    
    @Override
    public void zzce() {
        this.onAdClicked();
    }
    
    @Override
    public final void zzcf() {
        this.zzcb();
    }
    
    @Override
    public final void zzcg() {
        this.zzbo();
    }
    
    @Override
    public final void zzch() {
        this.zzcc();
    }
    
    @Override
    public final void zzci() {
        if (this.zzvw.zzacw != null) {
            final String zzbty = this.zzvw.zzacw.zzbty;
            zzakb.zzdk(new StringBuilder(String.valueOf(zzbty).length() + 74).append("Mediation adapter ").append(zzbty).append(" refreshed, but mediation adapters should never refresh.").toString());
        }
        this.zza(this.zzvw.zzacw, true);
        this.zzb(this.zzvw.zzacw, true);
        this.zzbq();
    }
    
    @Override
    public void zzcj() {
        this.recordImpression();
    }
    
    @Nullable
    public final String zzck() {
        if (this.zzvw.zzacw == null) {
            return null;
        }
        return zzc(this.zzvw.zzacw);
    }
    
    @Override
    public final void zzcl() {
        final Executor zzcvy = zzaoe.zzcvy;
        final zzbl zzvv = this.zzvv;
        zzvv.getClass();
        zzcvy.execute(zze.zza(zzvv));
    }
    
    @Override
    public final void zzcm() {
        final Executor zzcvy = zzaoe.zzcvy;
        final zzbl zzvv = this.zzvv;
        zzvv.getClass();
        zzcvy.execute(zzf.zza(zzvv));
    }
}
